[
   {
      "filename": "(\uc5ec\uc790)\uc544\uc774\ub4e4((G)I-DLE)_-_'LION'_Official_Music_Video.m4a",
      "artist id": "2AfmfGFbe0A0WsTYm0SDTx",
      "artist": "(G)I-DLE",
      "title": "Lion"
   },
   {
      "filename": "(\uc5ec\uc790)\uc544\uc774\ub4e4((G)I-DLE) - '\ub364\ub514\ub364\ub514 (DUMDi DUMDi)' Official Music Video.m4a",
      "artist id": "2AfmfGFbe0A0WsTYm0SDTx",
      "artist": "(G)I-DLE",
      "title": "Dumdi dumdi"
   },
   {
      "filename": "aespa \uc5d0\uc2a4\ud30c 'Forever (\uc57d\uc18d)' MV.m4a",
      "artist id": "6YVMFz59CuY7ngCxTxjpxE",
      "artist": "AESPA",
      "title": "forever"
   },
   {
      "filename": "AleXa (\uc54c\ub809\uc0ac) \u2013 \u201cKitty Run\u201d Performance.m4a",
      "artist id": "4jCGRzuZkwo8CxboiANMEU",
      "artist": "AleXa",
      "title": "kitty run"
   },
   {
      "filename": "AleXa (\uc54c\ub809\uc0ac) \u2013 -Villain- Official MV.m4a",
      "artist id": "4jCGRzuZkwo8CxboiANMEU",
      "artist": "AleXa",
      "title": "villain"
   },
   {
      "filename": "AleXa (\uc54c\ub809\uc0ac) \u2013 -Do Or Die- Official MV.m4a",
      "artist id": "4jCGRzuZkwo8CxboiANMEU",
      "artist": "AleXa",
      "title": "do or die"
   },
   {
      "filename": "AleXa (\uc54c\ub809\uc0ac) \u2013 -Bomb- Official MV.m4a",
      "artist id": "4jCGRzuZkwo8CxboiANMEU",
      "artist": "AleXa",
      "title": "bomb"
   },
   {
      "filename": "AOA_-_\u300cOh_BOY\u300dMusic_Video.m4a",
      "artist id": "54gWVQFHf8IIqbjxAoOarN",
      "artist": "AOA",
      "title": "oh boy"
   },
   {
      "filename": "AOA_(\uc5d0\uc774\uc624\uc5d0\uc774)_-_'MAGIC_SPELL'_(\uc8fc\ubb38\uc744_\uc678\uc6cc\ubd10)_Lyrics_[Color_Coded_Han_Rom_Eng].m4a",
      "artist id": "54gWVQFHf8IIqbjxAoOarN",
      "artist": "AOA",
      "title": "magic spell"
   },
   {
      "filename": "AOA_\u2013_\u2018\ub0a0_\ubcf4\ub7ec_\uc640\uc694_(Come_See_Me)\u2019_MUSIC_VIDEO.m4a",
      "artist id": "54gWVQFHf8IIqbjxAoOarN",
      "artist": "AOA",
      "title": "come see me"
   },
   {
      "filename": "[AOA_-_Super_Duper]_Comeback_Stage_-_M_COUNTDOWN_180531_EP.572.m4a",
      "artist id": "54gWVQFHf8IIqbjxAoOarN",
      "artist": "AOA",
      "title": "super duper"
   },
   {
      "filename": "[MV]_AOA___Bingle_Bangle(\ube59\uae00\ubc45\uae00).m4a",
      "artist id": "54gWVQFHf8IIqbjxAoOarN",
      "artist": "AOA",
      "title": "bingle bangle"
   },
   {
      "filename": "[MV]_Apink(\uc5d0\uc774\ud551\ud06c)___LUV.m4a",
      "artist id": "2uWcrwgWmZcQc3IPBs3tfU",
      "artist": "Apink",
      "title": "luv"
   },
   {
      "filename": "[MV]_Apink(\uc5d0\uc774\ud551\ud06c)___NoNoNo.m4a",
      "artist id": "2uWcrwgWmZcQc3IPBs3tfU",
      "artist": "Apink",
      "title": "nonono"
   },
   {
      "filename": "[MV] Apink(\uc5d0\uc774\ud551\ud06c) _ Dumhdurum(\ub364\ub354\ub7fc).m4a",
      "artist id": "2uWcrwgWmZcQc3IPBs3tfU",
      "artist": "Apink",
      "title": "dumhdurum"
   },
   {
      "filename": "Apink(\uc5d0\uc774\ud551\ud06c) - MOMENT(\ub108\uc758 \ubaa8\ub4e0 \uc21c\uac04\uc744 \uc0ac\ub791\ud574) @\uc778\uae30\uac00\uc694 inkigayo 20200419.m4a",
      "artist id": "2uWcrwgWmZcQc3IPBs3tfU",
      "artist": "Apink",
      "title": "moment"
   },
   {
      "filename": "[MV] Apink(\uc5d0\uc774\ud551\ud06c) _ %%(Eung Eung(\uc751\uc751)).m4a",
      "artist id": "2uWcrwgWmZcQc3IPBs3tfU",
      "artist": "Apink",
      "title": "eung eung"
   },
   {
      "filename": "[MV]_Apink(\uc5d0\uc774\ud551\ud06c)___Secret_Garden.m4a",
      "artist id": "2uWcrwgWmZcQc3IPBs3tfU",
      "artist": "Apink",
      "title": "secret garden"
   },
   {
      "filename": "[MV]_Apink(\uc5d0\uc774\ud551\ud06c)___Mr._Chu(\ubbf8\uc2a4\ud130_\uce04).m4a",
      "artist id": "2uWcrwgWmZcQc3IPBs3tfU",
      "artist": "Apink",
      "title": "mr. chu"
   },
   {
      "filename": "[MV]_Apink(\uc5d0\uc774\ud551\ud06c)___U_You.m4a",
      "artist id": "2uWcrwgWmZcQc3IPBs3tfU",
      "artist": "Apink",
      "title": "u you"
   },
   {
      "filename": "APRIL (\uc5d0\uc774\ud504\ub9b4) Oops I'm Sorry (\uc6c1\uc2a4 \uc544\uc784 \uc3d8\ub9ac) \uad50\ucc28\ud3b8\uc9d1 (Stage Mix).m4a",
      "artist id": "4cJ99wTjC60pXcfyISL9fa",
      "artist": "APRIL",
      "title": "oops I'm sorry"
   },
   {
      "filename": "[MV] APRIL(\uc5d0\uc774\ud504\ub9b4) _ MAYDAY.m4a",
      "artist id": "4cJ99wTjC60pXcfyISL9fa",
      "artist": "APRIL",
      "title": "mayday"
   },
   {
      "filename": "[MV] APRIL(\uc5d0\uc774\ud504\ub9b4) - Now or Never Music Video.m4a",
      "artist id": "4cJ99wTjC60pXcfyISL9fa",
      "artist": "APRIL",
      "title": "now or never"
   },
   {
      "filename": "April (\uc5d0\uc774\ud504\ub9b4) - PARADISE Lyrics (Han_Rom_Eng_Color Coded_Lyrics_\uac00\uc0ac) - bingsoosh.m4a",
      "artist id": "4cJ99wTjC60pXcfyISL9fa",
      "artist": "APRIL",
      "title": "paradise"
   },
   {
      "filename": "[MV] APRIL(\uc5d0\uc774\ud504\ub9b4) _ LALALILALA.m4a",
      "artist id": "4cJ99wTjC60pXcfyISL9fa",
      "artist": "APRIL",
      "title": "lalalilala"
   },
   {
      "filename": "BLACKPINK You Never Know Lyrics (\ube14\ub799\ud551\ud06c You Never Know \uac00\uc0ac) [Color Coded Lyrics_Han_Rom_Eng].m4a",
      "artist id": "41MozSoPIsD1dJM0CLPjZF",
      "artist": "BlackPink",
      "title": "you never know"
   },
   {
      "filename": "BLACKPINK Love To Hate Me Lyrics (Color Coded Lyrics).m4a",
      "artist id": "41MozSoPIsD1dJM0CLPjZF",
      "artist": "BlackPink",
      "title": "love to hate me"
   },
   {
      "filename": "BLACKPINK Crazy Over You Lyrics (\ube14\ub799\ud551\ud06c Crazy Over You \uac00\uc0ac) [Color Coded Lyrics_Eng].m4a",
      "artist id": "41MozSoPIsD1dJM0CLPjZF",
      "artist": "BlackPink",
      "title": "crazy over you"
   },
   {
      "filename": "BLACKPINK \u2013 \u2018Lovesick Girls\u2019  MV.m4a",
      "artist id": "41MozSoPIsD1dJM0CLPjZF",
      "artist": "BlackPink",
      "title": "lovesick girls"
   },
   {
      "filename": "BLACKPINK Pretty Savage Lyrics (\ube14\ub799\ud551\ud06c Pretty Savage \uac00\uc0ac) [Color Coded Lyrics_Han_Rom_Eng].m4a",
      "artist id": "41MozSoPIsD1dJM0CLPjZF",
      "artist": "BlackPink",
      "title": "pretty savage"
   },
   {
      "filename": "Cherry Bullet (\uccb4\ub9ac\ube14\ub81b) \u2013 Stick Out (\ub208\uc5d0 \ub744\ub124) Lyrics (Color Coded Han_Rom_Eng).m4a",
      "artist id": "3IJCdgkBZbieocLZ4e94GZ",
      "artist": "Cherry Bullet",
      "title": "stick out"
   },
   {
      "filename": "[MV]_\uccb4\ub9ac\ube14\ub81b(Cherry_Bullet)___Q&A.m4a",
      "artist id": "3IJCdgkBZbieocLZ4e94GZ",
      "artist": "Cherry Bullet",
      "title": "q&a"
   },
   {
      "filename": "Cherry Bullet (\uccb4\ub9ac\ube14\ub81b) - Violet Lyrics [Color Coded-Han_Rom_Eng].m4a",
      "artist id": "3IJCdgkBZbieocLZ4e94GZ",
      "artist": "Cherry Bullet",
      "title": "violet"
   },
   {
      "filename": "[MV] Cherry Bullet(\uccb4\ub9ac\ube14\ub81b) _ Hands Up(\ubb34\ub98e\uc744 \ud0c1 \uce58\uace0).m4a",
      "artist id": "3IJCdgkBZbieocLZ4e94GZ",
      "artist": "Cherry Bullet",
      "title": "hands up"
   },
   {
      "filename": "[MV] Cherry Bullet(\uccb4\ub9ac\ube14\ub81b) _ Aloha Oe(\uc54c\ub85c\ud558\uc624\uc5d0).m4a",
      "artist id": "3IJCdgkBZbieocLZ4e94GZ",
      "artist": "Cherry Bullet",
      "title": "aloha oe"
   },
   {
      "filename": "Cherry Bullet (\uccb4\ub9ac\ube14\ub81b) - Keep Your Head Up (\ud3fc \ub098\uac8c (Keep Your Head Up)).m4a",
      "artist id": "3IJCdgkBZbieocLZ4e94GZ",
      "artist": "Cherry Bullet",
      "title": "keep your head up"
   },
   {
      "filename": "Cherry Bullet (\uccb4\ub9ac\ube14\ub81b) - Whatever (\uba4b\ub300\ub85c \ud574) Lyrics [Color Coded-Han_Rom_Eng].m4a",
      "artist id": "3IJCdgkBZbieocLZ4e94GZ",
      "artist": "Cherry Bullet",
      "title": "whatever"
   },
   {
      "filename": "[MV]_Cherry_Bullet(\uccb4\ub9ac\ube14\ub81b)___Really_Really(\ub124\uac00_\ucc38_\uc88b\uc544).m4a",
      "artist id": "3IJCdgkBZbieocLZ4e94GZ",
      "artist": "Cherry Bullet",
      "title": "really really"
   },
   {
      "filename": "\uccb4\ub9ac\ube14\ub81b (Cherry Bullet) - 'Love So Sweet' MV.m4a",
      "artist id": "3IJCdgkBZbieocLZ4e94GZ",
      "artist": "Cherry Bullet",
      "title": "love so sweet"
   },
   {
      "filename": "Cherry Bullet (\uccb4\ub9ac\ube14\ub81b) - (\ub77c\ud31c\ud30c) Follow Me (Color Coded Lyrics Eng_Rom_Han_\uac00\uc0ac).m4a",
      "artist id": "3IJCdgkBZbieocLZ4e94GZ",
      "artist": "Cherry Bullet",
      "title": "follow me"
   },
   {
      "filename": "\uc2dc\uadf8\ub2c8\ucc98 (cignature) - '\uc544\uc2f8 (ASSA)' MV.m4a",
      "artist id": "5x9WawpXGR82PWDFk9CKYQ",
      "artist": "Cignature",
      "title": "assa"
   },
   {
      "filename": "\uc2dc\uadf8\ub2c8\ucc98 (Cignature) - \ub208\ub204\ub09c\ub098 (Nun Nu Nan Na) [MV].m4a",
      "artist id": "5x9WawpXGR82PWDFk9CKYQ",
      "artist": "Cignature",
      "title": "nun nu nan na"
   },
   {
      "filename": "CLC(\uc528\uc5d8\uc528)_-_'\uc990\uaca8_(I_LIKE_IT)'_(Performance_Video).m4a",
      "artist id": "6QyO41KctzGc70mVaVnXQO",
      "artist": "CLC",
      "title": "I like it"
   },
   {
      "filename": "CLC(\uc528\uc5d8\uc528)_-_'Devil'_Official_Music_Video.m4a",
      "artist id": "6QyO41KctzGc70mVaVnXQO",
      "artist": "CLC",
      "title": "devil"
   },
   {
      "filename": "CLC(\uc528\uc5d8\uc528)_-_'\uc608\ubed0\uc9c0\uac8c(High_Heels)'.m4a",
      "artist id": "6QyO41KctzGc70mVaVnXQO",
      "artist": "CLC",
      "title": "high heels"
   },
   {
      "filename": "CLC(\uc528\uc5d8\uc528)_-_'SUMMER_KISS'_(Choreography_Practice_Video).m4a",
      "artist id": "6QyO41KctzGc70mVaVnXQO",
      "artist": "CLC",
      "title": "summer kiss"
   },
   {
      "filename": "CLC(\uc528\uc5d8\uc528) - 'HELICOPTER' Official Music Video.m4a",
      "artist id": "6QyO41KctzGc70mVaVnXQO",
      "artist": "CLC",
      "title": "helicopter"
   },
   {
      "filename": "\uc528\uc5d8\uc528(CLC)_-_'\uad81\uae08\ud574_(Like)'.m4a",
      "artist id": "6QyO41KctzGc70mVaVnXQO",
      "artist": "CLC",
      "title": "like"
   },
   {
      "filename": "[MV]_CLC___No_Oh_Oh(\uc544\ub2c8\uc57c).m4a",
      "artist id": "6QyO41KctzGc70mVaVnXQO",
      "artist": "CLC",
      "title": "no oh oh"
   },
   {
      "filename": "[Special_Clip]_Dreamcatcher(\ub4dc\ub9bc\uce90\uccd0)___Emotion_(\uc18c\uc6d0\ud558\ub098).m4a",
      "artist id": "5V1qsQHdXNm4ZEZHWvFnqQ",
      "artist": "DreamCatcher",
      "title": "emotion"
   },
   {
      "filename": "Dreamcatcher(\ub4dc\ub9bc\uce90\uccd0) - Break the Wall.m4a",
      "artist id": "5V1qsQHdXNm4ZEZHWvFnqQ",
      "artist": "DreamCatcher",
      "title": "break the wall"
   },
   {
      "filename": "DREAMCATCHER (\ub4dc\ub9bc\uce90\uccd0)  - \u2018New Days (\uc2dc\uac04\uc758 \ud2c8)\u2019 Color Coded Lyrics Eng_Rom_Han.m4a",
      "artist id": "5V1qsQHdXNm4ZEZHWvFnqQ",
      "artist": "DreamCatcher",
      "title": "new days"
   },
   {
      "filename": "Dreamcatcher_(\ub4dc\ub9bc\uce90\uccd0)_-_'Which_A_Star_(\uc5b4\ub290_\ubcc4)'_Lyrics_(Color_Coded_Han-Rom).m4a",
      "artist id": "5V1qsQHdXNm4ZEZHWvFnqQ",
      "artist": "DreamCatcher",
      "title": "which a star"
   },
   {
      "filename": "DREAMCATCHER (\ub4dc\ub9bc\uce90\uccd0) -\u2018Wind Blows (\ubc14\ub78c\uc774)\u2019 Color Coded Lyrics Eng_Rom_Han.m4a",
      "artist id": "5V1qsQHdXNm4ZEZHWvFnqQ",
      "artist": "DreamCatcher",
      "title": "wind blows"
   },
   {
      "filename": "Dreamcatcher(\ub4dc\ub9bc\uce90\uccd0) 'Odd Eye' MV.m4a",
      "artist id": "5V1qsQHdXNm4ZEZHWvFnqQ",
      "artist": "DreamCatcher",
      "title": "odd eye"
   },
   {
      "filename": "DREAMCATCHER_(\ub4dc\ub9bc\uce90\uccd0)_-_'SILENT_NIGHT'_Lyrics_[Color_Coded_Han_Rom_Eng].m4a",
      "artist id": "5V1qsQHdXNm4ZEZHWvFnqQ",
      "artist": "DreamCatcher",
      "title": "silent night"
   },
   {
      "filename": "Dreamcatcher(\ub4dc\ub9bc\uce90\uccd0) 'BOCA' MV.m4a",
      "artist id": "5V1qsQHdXNm4ZEZHWvFnqQ",
      "artist": "DreamCatcher",
      "title": "boca"
   },
   {
      "filename": "Daydream_(\ubc31\uc77c\ubabd)_-_Dreamcatcher_Lyrics_(Color_Coded)_[ENG_ROM].m4a",
      "artist id": "5V1qsQHdXNm4ZEZHWvFnqQ",
      "artist": "DreamCatcher",
      "title": "daydream"
   },
   {
      "filename": "[Special Clip] Dreamcatcher(\ub4dc\ub9bc\uce90\uccd0) 'Red Sun'.m4a",
      "artist id": "5V1qsQHdXNm4ZEZHWvFnqQ",
      "artist": "DreamCatcher",
      "title": "red sun"
   },
   {
      "filename": "[MV]_DREAMCATCHER\u300cBreaking_Out\u300d(1st_Japan_AL\u300cThe_Beginning_Of_The_End\u300d).m4a",
      "artist id": "5V1qsQHdXNm4ZEZHWvFnqQ",
      "artist": "DreamCatcher",
      "title": "breaking out"
   },
   {
      "filename": "Dreamcatcher(\ub4dc\ub9bc\uce90\uccd0)_'YOU_AND_I'_MV.m4a",
      "artist id": "5V1qsQHdXNm4ZEZHWvFnqQ",
      "artist": "DreamCatcher",
      "title": "you and i"
   },
   {
      "filename": "Dreamcatcher(\ub4dc\ub9bc\uce90\uccd0)_'\ub370\uc790\ubd80_(Deja_Vu)'_MV.m4a",
      "artist id": "5V1qsQHdXNm4ZEZHWvFnqQ",
      "artist": "DreamCatcher",
      "title": "deja vu"
   },
   {
      "filename": "[Special_Clip]_Dreamcatcher(\ub4dc\ub9bc\uce90\uccd0)_\uc2dc\uc5f0_'We_All_Lie'.m4a",
      "artist id": "5V1qsQHdXNm4ZEZHWvFnqQ",
      "artist": "DreamCatcher",
      "title": "we all lie"
   },
   {
      "filename": "[Special_Clip]_Dreamcatcher(\ub4dc\ub9bc\uce90\uccd0)___Lucky_Strike.m4a",
      "artist id": "5V1qsQHdXNm4ZEZHWvFnqQ",
      "artist": "DreamCatcher",
      "title": "lucky strike"
   },
   {
      "filename": "Dreamcatcher (\ub4dc\ub9bc\uce90\uccd0) - \u2018Can\u2019t get you out of my mind\u2019  Color Coded Lyrics Eng_Rom_Han_\uac00\uc0ac.m4a",
      "artist id": "5V1qsQHdXNm4ZEZHWvFnqQ",
      "artist": "DreamCatcher",
      "title": "can't get you out of my mind"
   },
   {
      "filename": "Dreamcatcher_(\ub4dc\ub9bc\uce90\uccd0)_\u2013_'Scar_(\uc774_\ub354\ub7fd\uace0\ub3c4_\ucd94\ud55c\u2026)'_Lyrics_[HAN_ROM_ENG]_(Color_Coded).m4a",
      "artist id": "5V1qsQHdXNm4ZEZHWvFnqQ",
      "artist": "DreamCatcher",
      "title": "scar"
   },
   {
      "filename": "[Special_Clip]_Dreamcatcher(\ub4dc\ub9bc\uce90\uccd0)_'\uc57d\uc18d\ud574_\uc6b0\ub9ac(July_7th)'_4K.m4a",
      "artist id": "5V1qsQHdXNm4ZEZHWvFnqQ",
      "artist": "DreamCatcher",
      "title": "july 7th"
   },
   {
      "filename": "[Special_Clip]_Dreamcatcher(\ub4dc\ub9bc\uce90\uccd0)_\uc9c0\uc720_'Honesty'.m4a",
      "artist id": "5V1qsQHdXNm4ZEZHWvFnqQ",
      "artist": "DreamCatcher",
      "title": "honesty"
   },
   {
      "filename": "Dreamcatcher_(\ub4dc\ub9bc\uce90\uccd0)_\u2013_Lullaby_(\ub8f0\ub77c\ubc14\uc774)_Lyrics_[Color_Coded_Han_Rom_Eng].m4a",
      "artist id": "5V1qsQHdXNm4ZEZHWvFnqQ",
      "artist": "DreamCatcher",
      "title": "lullaby"
   },
   {
      "filename": "[Special_Clip]_Dreamcatcher(\ub4dc\ub9bc\uce90\uccd0)_'And_There_Was_No_One_Left'.m4a",
      "artist id": "5V1qsQHdXNm4ZEZHWvFnqQ",
      "artist": "DreamCatcher",
      "title": "and there was no one left"
   },
   {
      "filename": "[Special_Clip]_Dreamcatcher(\ub4dc\ub9bc\uce90\uccd0)_'\uad1c\ucc2e\uc544!'.m4a",
      "artist id": "5V1qsQHdXNm4ZEZHWvFnqQ",
      "artist": "DreamCatcher",
      "title": "trust me"
   },
   {
      "filename": "Dreamcatcher_(\ub4dc\ub9bc\uce90\uccd0)_\u2013_'Mayday'_Lyrics_[HAN_ROM_ENG]_(Color_Coded).m4a",
      "artist id": "5V1qsQHdXNm4ZEZHWvFnqQ",
      "artist": "DreamCatcher",
      "title": "mayday"
   },
   {
      "filename": "[Special_Clip]_Dreamcatcher(\ub4dc\ub9bc\uce90\uccd0)_'Over_The_Sky'.m4a",
      "artist id": "5V1qsQHdXNm4ZEZHWvFnqQ",
      "artist": "DreamCatcher",
      "title": "over the sky"
   },
   {
      "filename": "Dreamcatcher(\ub4dc\ub9bc\uce90\uccd0)_-_Chase_Me_\uc548\ubb34\uc601\uc0c1(Dance_Video).m4a",
      "artist id": "5V1qsQHdXNm4ZEZHWvFnqQ",
      "artist": "DreamCatcher",
      "title": "chase me"
   },
   {
      "filename": "Dreamcatcher_(\ub4dc\ub9bc\uce90\uccd0)_\u2013_The_curse_of_the_Spider_(\uac70\ubbf8\uc758_\uc800\uc8fc)_(Color_Coded_Han_Rom_.m4a",
      "artist id": "5V1qsQHdXNm4ZEZHWvFnqQ",
      "artist": "DreamCatcher",
      "title": "the curse of the spider"
   },
   {
      "filename": "DREAMCATCHER_(\ub4dc\ub9bc\uce90\uccd0)_-_'POLARIS'_(\ubd81\uadf9\uc131)_Lyrics_[Color_Coded_Han_Rom_Eng].m4a",
      "artist id": "5V1qsQHdXNm4ZEZHWvFnqQ",
      "artist": "DreamCatcher",
      "title": "polaris"
   },
   {
      "filename": "Dreamcatcher (\ub4dc\ub9bc\uce90\uccd0) - \u2018Dear\u2019  Color Coded Lyrics Eng_Rom_Han_\uac00\uc0ac.m4a",
      "artist id": "5V1qsQHdXNm4ZEZHWvFnqQ",
      "artist": "DreamCatcher",
      "title": "dear"
   },
   {
      "filename": "DREAMCATCHER (\ub4dc\ub9bc\uce90\uccd0)  - \u20184 Memory\u2019 Color Coded Lyrics Eng_Rom_Han.m4a",
      "artist id": "5V1qsQHdXNm4ZEZHWvFnqQ",
      "artist": "DreamCatcher",
      "title": "4 memory"
   },
   {
      "filename": "Dreamcatcher_(\ub4dc\ub9bc\uce90\uccd0)_-_Trust_Me_(\uad1c\ucc2e\uc544)_Lyrics_[Color_Coded_Han_Rom_Eng].m4a",
      "artist id": "5V1qsQHdXNm4ZEZHWvFnqQ",
      "artist": "DreamCatcher",
      "title": "trust me"
   },
   {
      "filename": "[MV]_DreamNote(\ub4dc\ub9bc\ub178\ud2b8)___Hakuna_matata(\ud558\ucfe0\ub098_\ub9c8\ud0c0\ud0c0).m4a",
      "artist id": "3ILvL0HM0cST4iR8RzQh2V",
      "artist": "DreamNote",
      "title": "hakuna matata"
   },
   {
      "filename": "[MV]_DreamNote(\ub4dc\ub9bc\ub178\ud2b8)___DREAM_NOTE.m4a",
      "artist id": "3ILvL0HM0cST4iR8RzQh2V",
      "artist": "DreamNote",
      "title": "dream note"
   },
   {
      "filename": "EVERGLOW (\uc5d0\ubc84\uae00\ub85c\uc6b0) - 'Hush' (Color Coded Lyrics EngRomHan\uac00\uc0ac).m4a",
      "artist id": "3ZZzT0naD25RhY2uZvIKkJ",
      "artist": "Everglow",
      "title": "hush"
   },
   {
      "filename": "EVERGLOW (\uc5d0\ubc84\uae00\ub85c\uc6b0) - LA DI DA MV.m4a",
      "artist id": "3ZZzT0naD25RhY2uZvIKkJ",
      "artist": "Everglow",
      "title": "la di da"
   },
   {
      "filename": "EVERGLOW (\uc5d0\ubc84\uae00\ub85c\uc6b0) - Untouchable (Color Coded Lyrics Eng_Rom_Han_\uac00\uc0ac).m4a",
      "artist id": "3ZZzT0naD25RhY2uZvIKkJ",
      "artist": "Everglow",
      "title": "untouchable"
   },
   {
      "filename": "EVERGLOW PLAYER Lyrics (\uc5d0\ubc84\uae00\ub85c\uc6b0 PLAYER \uac00\uc0ac) [Color Coded Lyrics_Han_Rom_Eng].m4a",
      "artist id": "3ZZzT0naD25RhY2uZvIKkJ",
      "artist": "Everglow",
      "title": "player"
   },
   {
      "filename": "EVERGLOW (\uc5d0\ubc84\uae00\ub85c\uc6b0) \u2013 NO GOOD REASON Lyrics (Color Coded HanRomEng).m4a",
      "artist id": "3ZZzT0naD25RhY2uZvIKkJ",
      "artist": "Everglow",
      "title": "no good reason"
   },
   {
      "filename": "EVERGLOW - You Don't Know Me (\uc5d0\ubc84\uae00\ub85c\uc6b0 - You Don't Know Me) [Color Coded Lyrics_Han_Rom_Eng_\uac00\uc0ac].m4a",
      "artist id": "3ZZzT0naD25RhY2uZvIKkJ",
      "artist": "Everglow",
      "title": "you don't know me"
   },
   {
      "filename": "EVERGLOW (\uc5d0\ubc84\uae00\ub85c\uc6b0) - DUN DUN [MV].m4a",
      "artist id": "3ZZzT0naD25RhY2uZvIKkJ",
      "artist": "Everglow",
      "title": "dun dun"
   },
   {
      "filename": "EVERGLOW 'GxxD BOY' Lyrics (\uc5d0\ubc84\uae00\ub85c\uc6b0 GxxD BOY \uac00\uc0ac) Color Coded Lyrics - Peachthetics\uc9c0\ud6a8\ub2c8.m4a",
      "artist id": "3ZZzT0naD25RhY2uZvIKkJ",
      "artist": "Everglow",
      "title": "gxxd boy"
   },
   {
      "filename": "EXID_UP&DOWN\uff3bJAPANESE_VERSION\uff3dOFFICIAL_MV.m4a",
      "artist id": "1xs6WFotNQSXweo0GXrS0O",
      "artist": "EXID",
      "title": "up&down [japanese version]"
   },
   {
      "filename": "[MV]_\ud504\ub85c\ubbf8\uc2a4\ub098\uc778_(fromis_9)_-_FUN!.m4a",
      "artist id": "24nUVBIlCGi4twz4nYxJum",
      "artist": "Fromis_9",
      "title": "fun!"
   },
   {
      "filename": "[MV]_\ud504\ub85c\ubbf8\uc2a4\ub098\uc778_(fromis_9)_-_LOVE_BOMB.m4a",
      "artist id": "24nUVBIlCGi4twz4nYxJum",
      "artist": "Fromis_9",
      "title": "love bomb"
   },
   {
      "filename": "fromis_9_(\ud504\ub85c\ubbf8\uc2a4_9)_-_\uc720\ub9ac\uad6c\ub450_(Glass_Shoes)_MV.m4a",
      "artist id": "24nUVBIlCGi4twz4nYxJum",
      "artist": "Fromis_9",
      "title": "glass shoes"
   },
   {
      "filename": "\ud504\ub85c\ubbf8\uc2a4\ub098\uc778 (fromis_9) 'Feel Good (SECRET CODE)' MV.m4a",
      "artist id": "24nUVBIlCGi4twz4nYxJum",
      "artist": "Fromis_9",
      "title": "feel good"
   },
   {
      "filename": "fromis_9 (\ud504\ub85c\ubbf8\uc2a4\ub098\uc778) - Somebody to love (Han-Rom-Eng) Color Coded Lyrics_\ud55c\uad6d\uc5b4 \uac00\uc0ac.m4a",
      "artist id": "24nUVBIlCGi4twz4nYxJum",
      "artist": "Fromis_9",
      "title": "somebody to love"
   },
   {
      "filename": "Fromis_9 (\ud504\ub85c\ubbf8\uc2a4\ub098\uc778) - 'CLOVER' Lyrics (Color Coded Han_Rom_Eng).m4a",
      "artist id": "24nUVBIlCGi4twz4nYxJum",
      "artist": "Fromis_9",
      "title": "clover"
   },
   {
      "filename": "[fromis_9_-_LOVE_RUMPUMPUM]_KPOP_TV_Show_-_M_COUNTDOWN_190718_EP.628.m4a",
      "artist id": "24nUVBIlCGi4twz4nYxJum",
      "artist": "Fromis_9",
      "title": "rumpumpum"
   },
   {
      "filename": "fromis_9 (\ud504\ub85c\ubbf8\uc2a4\ub098\uc778) - Weather (Han-Rom-Eng) Color Coded Lyrics_\ud55c\uad6d\uc5b4 \uac00\uc0ac.m4a",
      "artist id": "24nUVBIlCGi4twz4nYxJum",
      "artist": "Fromis_9",
      "title": "weather"
   },
   {
      "filename": "FROMIS_9(\ud504\ub85c\ubbf8\uc2a4\ub098\uc778) \u201cSTARRY NIGHT(\ubcc4\uc758 \ubc24)\u201d Color Coded Lyrics [Han_Rom_Eng] \uac00\uc0ac.m4a",
      "artist id": "24nUVBIlCGi4twz4nYxJum",
      "artist": "Fromis_9",
      "title": "starry night"
   },
   {
      "filename": "\uc5ec\uc790\uce5c\uad6c_GFRIEND_X_AMERICAN_TOURISTER_-_\ud30c\ub3c4_M_V.m4a",
      "artist id": "0qlWcS66ohOIi0M8JZwPft",
      "artist": "GFRIEND",
      "title": "wave"
   },
   {
      "filename": "[MV]_GFRIEND(\uc5ec\uc790\uce5c\uad6c)___Me_Gustas_Tu(\uc624\ub298\ubd80\ud130_\uc6b0\ub9ac\ub294).m4a",
      "artist id": "0qlWcS66ohOIi0M8JZwPft",
      "artist": "GFRIEND",
      "title": "me gustas tu"
   },
   {
      "filename": "GFRIEND_(\uc5ec\uc790\uce5c\uad6c)_-_'VACATION'_Lyrics_[Color_Coded_Han_Rom_Eng].m4a",
      "artist id": "0qlWcS66ohOIi0M8JZwPft",
      "artist": "GFRIEND",
      "title": "vacation"
   },
   {
      "filename": "GFRIEND(\uc5ec\uc790\uce5c\uad6c)_-_Rain_In_The_Spring_Time(\ubd04\ube44)_Color_Coded_Lyrics_[Han_Rom_Eng].m4a",
      "artist id": "0qlWcS66ohOIi0M8JZwPft",
      "artist": "GFRIEND",
      "title": "rain in the spring time"
   },
   {
      "filename": "[MV]_GFRIEND(\uc5ec\uc790\uce5c\uad6c)___LOVE_WHISPER(\uadc0\ub97c_\uae30\uc6b8\uc774\uba74).m4a",
      "artist id": "0qlWcS66ohOIi0M8JZwPft",
      "artist": "GFRIEND",
      "title": "love whisper"
   },
   {
      "filename": "[MV]_GFRIEND(\uc5ec\uc790\uce5c\uad6c)___Time_for_the_moon_night(\ubc24).m4a",
      "artist id": "0qlWcS66ohOIi0M8JZwPft",
      "artist": "GFRIEND",
      "title": "time for the moon night"
   },
   {
      "filename": "GFRIEND_(\uc5ec\uc790\uce5c\uad6c)_-_'YOU_ARE_MY_STAR'_(\ubcc4)_Lyrics_[Color_Coded_Han_Rom_Eng].m4a",
      "artist id": "0qlWcS66ohOIi0M8JZwPft",
      "artist": "GFRIEND",
      "title": "you are my star"
   },
   {
      "filename": "[MV]_GFRIEND(\uc5ec\uc790\uce5c\uad6c)___Glass_Bead(\uc720\ub9ac\uad6c\uc2ac).m4a",
      "artist id": "0qlWcS66ohOIi0M8JZwPft",
      "artist": "GFRIEND",
      "title": "glas bead"
   },
   {
      "filename": "GFRIEND (\u110b\u1167\u110c\u1161\u110e\u1175\u11ab\u1100\u116e) 'MAGO' Official MV.m4a",
      "artist id": "0qlWcS66ohOIi0M8JZwPft",
      "artist": "GFRIEND",
      "title": "mago"
   },
   {
      "filename": "[MV]_GFRIEND(\uc5ec\uc790\uce5c\uad6c)___Summer_Rain(\uc5ec\ub984\ube44).m4a",
      "artist id": "0qlWcS66ohOIi0M8JZwPft",
      "artist": "GFRIEND",
      "title": "summer rain"
   },
   {
      "filename": "GFRIEND (\uc5ec\uc790\uce5c\uad6c) 'Apple' Official MV.m4a",
      "artist id": "0qlWcS66ohOIi0M8JZwPft",
      "artist": "GFRIEND",
      "title": "apple"
   },
   {
      "filename": "\uc5ec\uc790\uce5c\uad6c_GFRIEND_-_\uc5f4\ub300\uc57c_(Fever)_M_V.m4a",
      "artist id": "0qlWcS66ohOIi0M8JZwPft",
      "artist": "GFRIEND",
      "title": "fever"
   },
   {
      "filename": "[MV]_\uc5ec\uc790\uce5c\uad6c(GFRIEND)___\uc2dc\uac04\uc744_\ub2ec\ub824\uc11c(Rough).m4a",
      "artist id": "0qlWcS66ohOIi0M8JZwPft",
      "artist": "GFRIEND",
      "title": "rough"
   },
   {
      "filename": "[MV]_\uc5ec\uc790\uce5c\uad6c(GFRIEND)___\ub108_\uadf8\ub9ac\uace0_\ub098_(NAVILLERA).m4a",
      "artist id": "0qlWcS66ohOIi0M8JZwPft",
      "artist": "GFRIEND",
      "title": "navillera"
   },
   {
      "filename": "[MV]_EUNHA(\uc740\ud558_(\uc5ec\uc790\uce5c\uad6c)),_RAVI(\ub77c\ube44)___BLOSSOM_(Prod._Groovyroom).m4a",
      "artist id": "0qlWcS66ohOIi0M8JZwPft",
      "artist": "GFRIEND",
      "title": "blossom"
   },
   {
      "filename": "\u3010MV\u3011GFRIEND-FLOWER.m4a",
      "artist id": "0qlWcS66ohOIi0M8JZwPft",
      "artist": "GFRIEND",
      "title": "flower"
   },
   {
      "filename": "[MV]_GFRIEND(\uc5ec\uc790\uce5c\uad6c)___Sunrise(\ud574\uc57c).m4a",
      "artist id": "0qlWcS66ohOIi0M8JZwPft",
      "artist": "GFRIEND",
      "title": "sunrise"
   },
   {
      "filename": "GFRIEND_(\uc5ec\uc790\uce5c\uad6c)_-_Someday_(\uadf8\ub7f0_\ub0a0\uc5d4)_(Han_-_Rom_-_Eng_Color_Coded_Lyrics).m4a",
      "artist id": "0qlWcS66ohOIi0M8JZwPft",
      "artist": "GFRIEND",
      "title": "someday"
   },
   {
      "filename": "[MV]_GFRIEND(\uc5ec\uc790\uce5c\uad6c)___Sunny_Summer(\uc5ec\ub984\uc5ec\ub984\ud574).m4a",
      "artist id": "0qlWcS66ohOIi0M8JZwPft",
      "artist": "GFRIEND",
      "title": "sunny summer"
   },
   {
      "filename": "Girls\u2019_Generation_(\uc18c\ub140\uc2dc\ub300)_-_Light_Up_The_Sky_Lyrics_[Color_Coded_HAN_ROM_ENG].m4a",
      "artist id": "0Sadg1vgvaPqGTOjxu0N6c",
      "artist": "Girls' Generation",
      "title": "light up the sky"
   },
   {
      "filename": "Girls'_Generation_\uc18c\ub140\uc2dc\ub300_'Dancing_Queen'_MV.m4a",
      "artist id": "0Sadg1vgvaPqGTOjxu0N6c",
      "artist": "Girls' Generation",
      "title": "dancing queen"
   },
   {
      "filename": "Girls'_Generation_\uc18c\ub140\uc2dc\ub300_'Lion_Heart'_MV.m4a",
      "artist id": "0Sadg1vgvaPqGTOjxu0N6c",
      "artist": "Girls' Generation",
      "title": "lion heart"
   },
   {
      "filename": "Girls'_Generation_-_One_Last_Time_Lyrics_[Color_Coded_Han_Rom_Eng].m4a",
      "artist id": "0Sadg1vgvaPqGTOjxu0N6c",
      "artist": "Girls' Generation",
      "title": "one last time"
   },
   {
      "filename": "Girls'_Generation_\uc18c\ub140\uc2dc\ub300_'Mr.Mr.'_MV.m4a",
      "artist id": "0Sadg1vgvaPqGTOjxu0N6c",
      "artist": "Girls' Generation",
      "title": "mr. mr."
   },
   {
      "filename": "Girls'_Generation_\uc18c\ub140\uc2dc\ub300_'I_GOT_A_BOY'_MV.m4a",
      "artist id": "0Sadg1vgvaPqGTOjxu0N6c",
      "artist": "Girls' Generation",
      "title": "I got a boy"
   },
   {
      "filename": "Girls'_Generation_\uc18c\ub140\uc2dc\ub300_'Holiday'_MV.m4a",
      "artist id": "0Sadg1vgvaPqGTOjxu0N6c",
      "artist": "Girls' Generation",
      "title": "holiday"
   },
   {
      "filename": "Girls'_Generation-TTS_\uc18c\ub140\uc2dc\ub300-\ud0dc\ud2f0\uc11c_'Twinkle'_MV.m4a",
      "artist id": "0Sadg1vgvaPqGTOjxu0N6c",
      "artist": "Girls' Generation",
      "title": "twinkle"
   },
   {
      "filename": "GIRLS`_GENERATION_\u5c11\u5973\u6642\u4ee3_FLOWER_POWER_Music_Video.m4a",
      "artist id": "0Sadg1vgvaPqGTOjxu0N6c",
      "artist": "Girls' Generation",
      "title": "flower power"
   },
   {
      "filename": "Girls'_Generation___SNSD_(\u5c11\u5973\u6642\u4ee3)_-_Indestructible_lyrics_(JPN_ROM_ENG).m4a",
      "artist id": "0Sadg1vgvaPqGTOjxu0N6c",
      "artist": "Girls' Generation",
      "title": "indestructable"
   },
   {
      "filename": "Girls'_Generation_\u5c11\u5973\u6642\u4ee3_'PAPARAZZI'_MV.m4a",
      "artist id": "0Sadg1vgvaPqGTOjxu0N6c",
      "artist": "Girls' Generation",
      "title": "paparazzi"
   },
   {
      "filename": "SNSD_-_Galaxy_Supernova.m4a",
      "artist id": "0Sadg1vgvaPqGTOjxu0N6c",
      "artist": "Girls' Generation",
      "title": "galaxy supernova"
   },
   {
      "filename": "Girls'_Generation_\uc18c\ub140\uc2dc\ub300_'Oh!'_MV.m4a",
      "artist id": "0Sadg1vgvaPqGTOjxu0N6c",
      "artist": "Girls' Generation",
      "title": "oh!"
   },
   {
      "filename": "Girls'_Generation_\uc18c\ub140\uc2dc\ub300_'\ud6d7_(Hoot)'_MV.m4a",
      "artist id": "0Sadg1vgvaPqGTOjxu0N6c",
      "artist": "Girls' Generation",
      "title": "hoot"
   },
   {
      "filename": "ITZY 'iD' Lyrics (\uc788\uc9c0 iD \uac00\uc0ac) (Color Coded Lyrics).m4a",
      "artist id": "2KC9Qb60EaY0kW4eH68vr3",
      "artist": "ITZY",
      "title": "id"
   },
   {
      "filename": "ITZY 'Don't Give A What' Lyrics (\uc788\uc9c0 Don't Give A What \uac00\uc0ac) (Color Coded Lyrics).m4a",
      "artist id": "2KC9Qb60EaY0kW4eH68vr3",
      "artist": "ITZY",
      "title": "don\u2019t give a what"
   },
   {
      "filename": "ITZY \u201cNot Shy\u201d MV.m4a",
      "artist id": "2KC9Qb60EaY0kW4eH68vr3",
      "artist": "ITZY",
      "title": "not shy"
   },
   {
      "filename": "ITZY (\uc788\uc9c0) - Surf (Color Coded Lyrics Eng_Rom_Han_\uac00\uc0ac).m4a",
      "artist id": "2KC9Qb60EaY0kW4eH68vr3",
      "artist": "ITZY",
      "title": "surf"
   },
   {
      "filename": "IU(\uc544\uc774\uc720)___YOU&I(\ub108\ub791\ub098)_MV.m4a",
      "artist id": "3HqSLMAZ3g3d5poNaI7GOU",
      "artist": "IU",
      "title": "you&i"
   },
   {
      "filename": "[MV] IU(\uc544\uc774\uc720) _ Celebrity.m4a",
      "artist id": "3HqSLMAZ3g3d5poNaI7GOU",
      "artist": "IU",
      "title": "celebrity"
   },
   {
      "filename": "[MV]_IU(\uc544\uc774\uc720)___The_red_shoes(\ubd84\ud64d\uc2e0)_(Performance_ver.).m4a",
      "artist id": "3HqSLMAZ3g3d5poNaI7GOU",
      "artist": "IU",
      "title": "the read shoes"
   },
   {
      "filename": "[MV]_IU(\uc544\uc774\uc720)___Naui_Yetnal_Iyagi(\ub098\uc758_\uc61b\ub0a0\uc774\uc57c\uae30)_-_My_old_story.m4a",
      "artist id": "3HqSLMAZ3g3d5poNaI7GOU",
      "artist": "IU",
      "title": "my old story"
   },
   {
      "filename": "[MV] IU(\uc544\uc774\uc720) _ Through the Night(\ubc24\ud3b8\uc9c0).m4a",
      "artist id": "3HqSLMAZ3g3d5poNaI7GOU",
      "artist": "IU",
      "title": "through the night"
   },
   {
      "filename": "[MV]_IU(\uc544\uc774\uc720)___Blueming(\ube14\ub8e8\ubc0d).m4a",
      "artist id": "3HqSLMAZ3g3d5poNaI7GOU",
      "artist": "IU",
      "title": "blueming"
   },
   {
      "filename": "[MV]_IU(\uc544\uc774\uc720)___Twenty-three(\uc2a4\ubb3c\uc14b).m4a",
      "artist id": "3HqSLMAZ3g3d5poNaI7GOU",
      "artist": "IU",
      "title": "twenty-three"
   },
   {
      "filename": "[MV] IU(\uc544\uc774\uc720) _ Palette(\ud314\ub808\ud2b8) (Feat. G-DRAGON).m4a",
      "artist id": "3HqSLMAZ3g3d5poNaI7GOU",
      "artist": "IU",
      "title": "palette"
   },
   {
      "filename": "IU_(\uc544\uc774\uc720)___Good_Day_(\uc88b\uc740_\ub0a0)___MV.m4a",
      "artist id": "3HqSLMAZ3g3d5poNaI7GOU",
      "artist": "IU",
      "title": "good day"
   },
   {
      "filename": "[MV] IU(\uc544\uc774\uc720) - eight(\uc5d0\uc787) (Prod.&Feat. SUGA of BTS).m4a",
      "artist id": "3HqSLMAZ3g3d5poNaI7GOU",
      "artist": "IU",
      "title": "eight(Prod.&Feat. SUGA of BTS)"
   },
   {
      "filename": "[MV] IU(\uc544\uc774\uc720) _ \uc5b4\uc82f\ubc24 \uc774\uc57c\uae30 [Eojetbam Iyagi] - Last night story.m4a",
      "artist id": "3HqSLMAZ3g3d5poNaI7GOU",
      "artist": "IU",
      "title": "last night story"
   },
   {
      "filename": "[MV] IU(\uc544\uc774\uc720) _ Ending Scene(\uc774\ub7f0\u00a0\uc5d4\ub529).m4a",
      "artist id": "3HqSLMAZ3g3d5poNaI7GOU",
      "artist": "IU",
      "title": "ending scene"
   },
   {
      "filename": "[MV]_IU(\uc544\uc774\uc720)___above_the_time(\uc2dc\uac04\uc758_\ubc14\uae65).m4a",
      "artist id": "3HqSLMAZ3g3d5poNaI7GOU",
      "artist": "IU",
      "title": "above the time"
   },
   {
      "filename": "[MV] HIGH4, IU(\ud558\uc774\ud3ec, \uc544\uc774\uc720) _ Not Spring, Love, or Cherry Blossoms(\ubd04,\uc0ac\ub791,\ubc9a\uaf43 \ub9d0\uace0).m4a",
      "artist id": "3HqSLMAZ3g3d5poNaI7GOU",
      "artist": "IU",
      "title": "Not Spring, Love, or Cherry Blossoms"
   },
   {
      "filename": "IU The Sea of a Kid & I Lyrics (\u110b\u1161\u110b\u1175\u110b\u1172 \u110b\u1161\u110b\u1175\u110b\u116a \u1102\u1161\u110b\u1174 \u1107\u1161\u1103\u1161 \u1100\u1161\u1109\u1161) [Color Coded Lyrics_Han_Rom_Eng].m4a",
      "artist id": "3HqSLMAZ3g3d5poNaI7GOU",
      "artist": "IU",
      "title": "the sea of a kid & i"
   },
   {
      "filename": "IU AH PUH Lyrics (\u110b\u1161\u110b\u1175\u110b\u1172 \u110b\u1165\u1111\u116e \u1100\u1161\u1109\u1161)  (Color Coded Lyrics).m4a",
      "artist id": "3HqSLMAZ3g3d5poNaI7GOU",
      "artist": "IU",
      "title": "ah puh"
   },
   {
      "filename": "IU FLU Lyrics (\u110b\u1161\u110b\u1175\u110b\u1172 FLU \u1100\u1161\u1109\u1161)  (Color Coded Lyrics).m4a",
      "artist id": "3HqSLMAZ3g3d5poNaI7GOU",
      "artist": "IU",
      "title": "flu"
   },
   {
      "filename": "IZ-ONE_(\uc544\uc774\uc988\uc6d0)_-_'Buenos_Aires'_MV.m4a",
      "artist id": "5r1tUTxVSgvBHnoDuDODPH",
      "artist": "IZ*ONE",
      "title": "buenos aires"
   },
   {
      "filename": "[MV] \u1109\u1169\u110b\u1172 (SOYOU) X \u110b\u1161\u110b\u1175\u110c\u1173\u110b\u116f\u11ab (IZ-ONE) - ZERO-ATTITUDE (Feat.pH-1).m4a",
      "artist id": "5r1tUTxVSgvBHnoDuDODPH",
      "artist": "IZ*ONE",
      "title": "attitude"
   },
   {
      "filename": "IZ-ONE_(\uc544\uc774\uc988\uc6d0)_-_'\u597d\u304d\u3068\u8a00\u308f\u305b\u305f\u3044_(Suki_to_Iwasetai)'_MV.m4a",
      "artist id": "5r1tUTxVSgvBHnoDuDODPH",
      "artist": "IZ*ONE",
      "title": "suki to iwasetai"
   },
   {
      "filename": "'\ucd5c\ucd08 \uacf5\uac1c' \uc544\uc774\uc988\uc6d0(IZ-ONE) - Pretty - IZ-ONE COMEBACK SHOW ONEIRIC DIARY.m4a",
      "artist id": "5r1tUTxVSgvBHnoDuDODPH",
      "artist": "IZ*ONE",
      "title": "pretty"
   },
   {
      "filename": "IZ-ONE_(\uc544\uc774\uc988\uc6d0)_-_\ub77c\ube44\uc559\ub85c\uc988_(La_Vie_en_Rose)_MV.m4a",
      "artist id": "5r1tUTxVSgvBHnoDuDODPH",
      "artist": "IZ*ONE",
      "title": "la vie en rose"
   },
   {
      "filename": "IZ-ONE (\uc544\uc774\uc988\uc6d0) 'Someday (\uc5b8\uc820\uac00 \uc6b0\ub9ac\uc758 \ubc24\ub3c4 \uc9c0\ub098\uac00\uaca0\uc8e0)' (Color Coded Han_Rom_Eng Lyrics).m4a",
      "artist id": "5r1tUTxVSgvBHnoDuDODPH",
      "artist": "IZ*ONE",
      "title": "someday"
   },
   {
      "filename": "[Full_MV]_IZ-ONE_(\uc544\uc774\uc988\uc6d0)_-_Gokigen_Sayonara_(\u3054\u6a5f\u5acc\u30b5\u30e8\u30ca\u30e9).m4a",
      "artist id": "5r1tUTxVSgvBHnoDuDODPH",
      "artist": "IZ*ONE",
      "title": "gokigen sayonara"
   },
   {
      "filename": "IZ-ONE (\uc544\uc774\uc988\uc6d0) - \ud658\uc0c1\ub3d9\ud654 (Secret Story of the Swan) MV.m4a",
      "artist id": "5r1tUTxVSgvBHnoDuDODPH",
      "artist": "IZ*ONE",
      "title": "secret story of the swan"
   },
   {
      "filename": "[OFFICIAL VER.] IZ-ONE (\u30a2\u30a4\u30ba\u30ef\u30f3) - Yummy Summer Lyrics (Kan_Rom_Eng_Color Coded_Lyrics_\u6b4c\u8a5e).m4a",
      "artist id": "5r1tUTxVSgvBHnoDuDODPH",
      "artist": "IZ*ONE",
      "title": "yummy summer"
   },
   {
      "filename": "IZ-ONE_(\uc544\uc774\uc988\uc6d0)_-_'AIRPLANE'_Lyrics_[Color_Coded_Han_Rom_Eng].m4a",
      "artist id": "5r1tUTxVSgvBHnoDuDODPH",
      "artist": "IZ*ONE",
      "title": "airplane"
   },
   {
      "filename": "IZ-ONE_(\uc544\uc774\uc988\uc6d0)_-_'REALLY_LIKE_YOU'_Lyrics_[Color_Coded_Han_Rom_Eng].m4a",
      "artist id": "5r1tUTxVSgvBHnoDuDODPH",
      "artist": "IZ*ONE",
      "title": "really like you"
   },
   {
      "filename": "IZ-ONE_(\uc544\uc774\uc988\uc6d0)_-_\ube44\uc62c\ub808\ud0c0_(Violeta)_MV.m4a",
      "artist id": "5r1tUTxVSgvBHnoDuDODPH",
      "artist": "IZ*ONE",
      "title": "violeta"
   },
   {
      "filename": "IZ-ONE_(\uc544\uc774\uc988\uc6d0)_\u2013_Pick_Me_(\ub0b4\uaebc\uc57c)_(IZ-ONE_ver.)_(CD_only)_(Color_Coded_Lyrics_Ha.m4a",
      "artist id": "5r1tUTxVSgvBHnoDuDODPH",
      "artist": "IZ*ONE",
      "title": "pick me"
   },
   {
      "filename": "IZ-ONE_(\uc544\uc774\uc988\uc6d0)_-_'Vampire'_MV.m4a",
      "artist id": "5r1tUTxVSgvBHnoDuDODPH",
      "artist": "IZ*ONE",
      "title": "vampire"
   },
   {
      "filename": "IZ-ONE_(\uc544\uc774\uc988\uc6d0)_-_'Hey._Bae._Like_it.___Sunflower'_(\ud574\ubc14\ub77c\uae30)_Lyrics_[Color_Coded_.m4a",
      "artist id": "5r1tUTxVSgvBHnoDuDODPH",
      "artist": "IZ*ONE",
      "title": "hey bae like it"
   },
   {
      "filename": "IZ-ONE_(\uc544\uc774\uc988\uc6d0)_-_O'_My!_[HAN-ROM-ENG_Color_Coded_Lyrics].m4a",
      "artist id": "5r1tUTxVSgvBHnoDuDODPH",
      "artist": "IZ*ONE",
      "title": "o'  my!"
   },
   {
      "filename": "IZ-ONE_(\uc544\uc774\uc988\uc6d0)_-_Memory_(\ube44\ubc00\uc758_\uc2dc\uac04)_[HAN-ROM-ENG_Color_Coded_Lyrics].m4a",
      "artist id": "5r1tUTxVSgvBHnoDuDODPH",
      "artist": "IZ*ONE",
      "title": "memory"
   },
   {
      "filename": "IZ-ONE_(\uc544\uc774\uc988\uc6d0)_-_'UP___ABOVE_THE_SKY'_(\ud558\ub298_\uc704\ub85c)_Lyrics_[Color_Coded_Han_Rom_Eng.m4a",
      "artist id": "5r1tUTxVSgvBHnoDuDODPH",
      "artist": "IZ*ONE",
      "title": "above the sky"
   },
   {
      "filename": "IZ-ONE (\uc544\uc774\uc988\uc6d0) - 'Beware' MV.m4a",
      "artist id": "5r1tUTxVSgvBHnoDuDODPH",
      "artist": "IZ*ONE",
      "title": "beware"
   },
   {
      "filename": "IZ-ONE_(\uc544\uc774\uc988\uc6d0)_\u2013_AS_WE_DREAM_(\uafc8\uc744_\uafb8\ub294_\ub3d9\uc548)_(Coded_Lyrics_Eng_Rom_Han_\uac00\uc0ac).m4a",
      "artist id": "5r1tUTxVSgvBHnoDuDODPH",
      "artist": "IZ*ONE",
      "title": "as we dream"
   },
   {
      "filename": "[4K]_190206_IZ-ONE_IZONE_-_I_AM.m4a",
      "artist id": "5r1tUTxVSgvBHnoDuDODPH",
      "artist": "IZ*ONE",
      "title": "I am"
   },
   {
      "filename": "[4K]_190206_IZ-ONE_IZONE_-_NEKKOYA_(PICK_ME).m4a",
      "artist id": "5r1tUTxVSgvBHnoDuDODPH",
      "artist": "IZ*ONE",
      "title": "pick me"
   },
   {
      "filename": "IZ-ONE_(\uc544\uc774\uc988\uc6d0)_\u2013_YOU\u2019RE_IN_LOVE,_AREN\u2019T_YOU-_(\ubc18\ud574\ubc84\ub9ac\uc796\uc544;_\u597d\u304d\u306b\u306a\u3063\u3061\u3083\u3046\u3060\u308d\u3046\uff1f)_(Color_Co.m4a",
      "artist id": "5r1tUTxVSgvBHnoDuDODPH",
      "artist": "IZ*ONE",
      "title": "you're in love, aren't you"
   },
   {
      "filename": "IZ-ONE_(\uc544\uc774\uc988\uc6d0)_-_'LOVE_BUBBLE'_Lyrics_[Color_Coded_Han_Rom_Eng].m4a",
      "artist id": "5r1tUTxVSgvBHnoDuDODPH",
      "artist": "IZ*ONE",
      "title": "love bubble"
   },
   {
      "filename": "IZ-ONE_(\uc544\uc774\uc988\uc6d0)_-_'I_WANT_TO_BE_A_CAT'_(Korean_Version)_Lyrics_[Color_Coded_Ha.m4a",
      "artist id": "5r1tUTxVSgvBHnoDuDODPH",
      "artist": "IZ*ONE",
      "title": "I want to be a cat [korean version]"
   },
   {
      "filename": "IZ-ONE_(\uc544\uc774\uc988\uc6d0)_\u2013_WE_TOGETHER_(\uc55e\uc73c\ub85c_\uc798_\ubd80\ud0c1\ud574)_(Coded_Lyrics_Eng_Rom_Han_\uac00\uc0ac).m4a",
      "artist id": "5r1tUTxVSgvBHnoDuDODPH",
      "artist": "IZ*ONE",
      "title": "we together"
   },
   {
      "filename": "IZ-ONE_(\uc544\uc774\uc988\uc6d0)_\u2013_BEAUTIFUL_COLOR_(\uc544\ub984\ub2e4\uc6b4_\uc0c9)_(Coded_Lyrics_Eng_Rom_Han_\uac00\uc0ac).m4a",
      "artist id": "5r1tUTxVSgvBHnoDuDODPH",
      "artist": "IZ*ONE",
      "title": "beautiful color"
   },
   {
      "filename": "K_DA - I\u2019LL SHOW YOU ft. TWICE, Bekuh BOOM, Annika Wells (Official Audio).m4a",
      "artist id": "4gOc8TsQed9eqnqJct2c5v",
      "artist": "K/DA",
      "title": "I'll show you"
   },
   {
      "filename": "K_DA - MORE ft. Madison Beer, (G)I-DLE, Lexie Liu, Jaira Burns, Seraphine (Official Music Video).m4a",
      "artist id": "4gOc8TsQed9eqnqJct2c5v",
      "artist": "K/DA",
      "title": "more"
   },
   {
      "filename": "K_DA - DRUM GO DUM ft. Aluna, Wolftyla, Bekuh BOOM (Official Audio).m4a",
      "artist id": "4gOc8TsQed9eqnqJct2c5v",
      "artist": "K/DA",
      "title": "drum go dum"
   },
   {
      "filename": "K_DA - VILLAIN ft. Madison Beer and Kim Petras (Official Audio).m4a",
      "artist id": "4gOc8TsQed9eqnqJct2c5v",
      "artist": "K/DA",
      "title": "villain"
   },
   {
      "filename": "LOONA (\uc774\ub2ec\uc758 \uc18c\ub140) \u2013 Universe (Han-Rom-Eng) Color Coded Lyrics_\ud55c\uad6d\uc5b4 \uac00\uc0ac.m4a",
      "artist id": "52zMTJCKluDlFwMQWmccY7",
      "artist": "LOONA",
      "title": "universe"
   },
   {
      "filename": "[MV] \uc774\ub2ec\uc758 \uc18c\ub140 \uc624\ub4dc\uc544\uc774\uc368\ud074 (LOONA_ODD EYE CIRCLE) - Girl Front.m4a",
      "artist id": "52zMTJCKluDlFwMQWmccY7",
      "artist": "LOONA",
      "title": "girl front"
   },
   {
      "filename": "[MV]_\uc774\ub2ec\uc758_\uc18c\ub140_(LOONA)_-Hi_High.m4a",
      "artist id": "52zMTJCKluDlFwMQWmccY7",
      "artist": "LOONA",
      "title": "hi high"
   },
   {
      "filename": "[MV] \uc774\ub2ec\uc758 \uc18c\ub140 (LOONA) So What.m4a",
      "artist id": "52zMTJCKluDlFwMQWmccY7",
      "artist": "LOONA",
      "title": "so what"
   },
   {
      "filename": "LOONA \u110b\u1175\u1103\u1161\u11af\u110b\u1174 \u1109\u1169\u1102\u1167 - Hide & Seek (\u1109\u116e\u11b7\u1107\u1161\u1101\u1169\u11a8\u110c\u1175\u11af) - Lyrics (ColorCoded_ENG_HAN_ROM_\u1100\u1161\u1109\u1161).m4a",
      "artist id": "52zMTJCKluDlFwMQWmccY7",
      "artist": "LOONA",
      "title": "hide & seek"
   },
   {
      "filename": "LOONA (\uc774\ub2ec\uc758 \uc18c\ub140) \u2013 Fall Again (\uae30\uc5b5\ud574) (Han-Rom-Eng) Color Coded Lyrics_\ud55c\uad6d\uc5b4 \uac00\uc0ac.m4a",
      "artist id": "52zMTJCKluDlFwMQWmccY7",
      "artist": "LOONA",
      "title": "fall again"
   },
   {
      "filename": "LOONA (\uc774\ub2ec\uc758 \uc18c\ub140) - (\uc548\uac2f\uae38) Misty Road (Cover) (\ubca4 (Ben)) (Han-Rom-Eng) Color Coded Lyrics_\ud55c\uad6d\uc5b4 \uac00\uc0ac.m4a",
      "artist id": "52zMTJCKluDlFwMQWmccY7",
      "artist": "LOONA",
      "title": "misty road"
   },
   {
      "filename": "[MV] \uc774\ub2ec\uc758 \uc18c\ub140 (LOONA) -Star-.m4a",
      "artist id": "52zMTJCKluDlFwMQWmccY7",
      "artist": "LOONA",
      "title": "star"
   },
   {
      "filename": "[MV] \uc774\ub2ec\uc758 \uc18c\ub140_\ud76c\uc9c4 (LOONA_HeeJin) -ViViD-.m4a",
      "artist id": "52zMTJCKluDlFwMQWmccY7",
      "artist": "LOONA",
      "title": "vivid"
   },
   {
      "filename": "\uc774\ub2ec\uc758 \uc18c\ub140(LOONA) \ud788\ub4e0\ud2b8\ub799 1\uc704\uace1- \uc704\uc131 (Satellite) | \ud558\uc774\ub77c\uc774\ud2b8 | \ubba4\uc9c1 \ub77c\uc774\ube0c\uc1fc [\ud788\ub4e0\ud2b8\ub7992].m4a",
      "artist id": "52zMTJCKluDlFwMQWmccY7",
      "artist": "LOONA",
      "title": "satellite"
   },
   {
      "filename": "LOONA \uc774\ub2ec\uc758 \uc18c\ub140 - OOPS! - Lyrics (ColorCoded_ENG_HAN_ROM_\uac00\uc0ac).m4a",
      "artist id": "52zMTJCKluDlFwMQWmccY7",
      "artist": "LOONA",
      "title": "oops!"
   },
   {
      "filename": "[MV]_\uc774\ub2ec\uc758_\uc18c\ub140_\uce04_(LOONA_Chuu)_-Heart_Attack.m4a",
      "artist id": "52zMTJCKluDlFwMQWmccY7",
      "artist": "LOONA",
      "title": "heart attack"
   },
   {
      "filename": "[MV] \uc774\ub2ec\uc758 \uc18c\ub140 (LOONA) -Why Not--.m4a",
      "artist id": "52zMTJCKluDlFwMQWmccY7",
      "artist": "LOONA",
      "title": "why not"
   },
   {
      "filename": "LOONA(\uc774\ub2ec\uc758 \uc18c\ub140) \u201cVOICE(\ubaa9\uc18c\ub9ac\u201d Color Coded Lyrics [Han_Rom_Eng] \uac00\uc0ac.m4a",
      "artist id": "52zMTJCKluDlFwMQWmccY7",
      "artist": "LOONA",
      "title": "voice"
   },
   {
      "filename": "[MV] \uc774\ub2ec\uc758 \uc18c\ub140 yyxy (LOONAyyxy) - love4eva (feat. Grimes).m4a",
      "artist id": "52zMTJCKluDlFwMQWmccY7",
      "artist": "LOONA",
      "title": "love4eva"
   },
   {
      "filename": "LOONA (\uc774\ub2ec\uc758 \uc18c\ub140) \"365\" (Color Coded Lyrics Eng:Rom:Han)(720p).m4a",
      "artist id": "52zMTJCKluDlFwMQWmccY7",
      "artist": "LOONA",
      "title": 365
   },
   {
      "filename": "[MV] \uc774\ub2ec\uc758 \uc18c\ub140_\ucd5c\ub9ac (LOONA_Choerry) - Love Cherry Motion.m4a",
      "artist id": "52zMTJCKluDlFwMQWmccY7",
      "artist": "LOONA",
      "title": "love cherry motion"
   },
   {
      "filename": "Lovelyz \ub7ec\ube14\ub9ac\uc988 Mijoo , Sujeong & Yein - The Lyrics [ Romanization  Hangul  Translation ].m4a",
      "artist id": "3g34PW5oNmDBxMVUTzx2XK",
      "artist": "Lovelyz",
      "title": "the"
   },
   {
      "filename": "[MV]_Lovelyz(\ub7ec\ube14\ub9ac\uc988)___Shooting_Star(\uc791\ubcc4\ud558\ub098).m4a",
      "artist id": "3g34PW5oNmDBxMVUTzx2XK",
      "artist": "Lovelyz",
      "title": "shooting star"
   },
   {
      "filename": "\ub7ec\ube14\ub9ac\uc988(Lovelyz)_-\uc9c0\uae08,_\uc6b0\ub9ac-_Official_MV.m4a",
      "artist id": "3g34PW5oNmDBxMVUTzx2XK",
      "artist": "Lovelyz",
      "title": "now, we"
   },
   {
      "filename": "\ub7ec\ube14\ub9ac\uc988(Lovelyz)_-\uc885\uc18c\ub9ac_(Twinkle)-_Official_MV.m4a",
      "artist id": "3g34PW5oNmDBxMVUTzx2XK",
      "artist": "Lovelyz",
      "title": "twinkle"
   },
   {
      "filename": "\ub7ec\ube14\ub9ac\uc988(Lovelyz)_-_\uc0bc\uac01\ud615(Triangle)_\uad50\ucc28\ud3b8\uc9d1(stage_mix).m4a",
      "artist id": "3g34PW5oNmDBxMVUTzx2XK",
      "artist": "Lovelyz",
      "title": "triangle"
   },
   {
      "filename": "Lovelyz \ub7ec\ube14\ub9ac\uc988 - Never, Secret (\uc808\ub300, \ube44\ubc00) - Lyrics (ColorCoded_ENG_HAN_ROM_\uac00\uc0ac).m4a",
      "artist id": "3g34PW5oNmDBxMVUTzx2XK",
      "artist": "Lovelyz",
      "title": "naver, secret"
   },
   {
      "filename": "Lovelyz \ub7ec\ube14\ub9ac\uc988 - Worry Dolls (\uac71\uc815 \uc778\ud615) - Lyrics (ColorCoded_ENG_HAN_ROM_\uac00\uc0ac).m4a",
      "artist id": "3g34PW5oNmDBxMVUTzx2XK",
      "artist": "Lovelyz",
      "title": "worry dolls"
   },
   {
      "filename": "Lovelyz \ub7ec\ube14\ub9ac\uc988 - Hide and Seek \uc228\ubc14\uaf2d\uc9c8 Lyrics [ Romanization Hangul Translation ].m4a",
      "artist id": "3g34PW5oNmDBxMVUTzx2XK",
      "artist": "Lovelyz",
      "title": "hide and seek"
   },
   {
      "filename": "\ub7ec\ube14\ub9ac\uc988(Lovelyz)_-Ah-Choo-_Official_MV.m4a",
      "artist id": "3g34PW5oNmDBxMVUTzx2XK",
      "artist": "Lovelyz",
      "title": "ah choo"
   },
   {
      "filename": "[\uad50\ucc28\ud3b8\uc9d1_-_Stage_Mix]_\ub7ec\ube14\ub9ac\uc988_(Lovelyz)_-_Rewind_(1st_week).m4a",
      "artist id": "3g34PW5oNmDBxMVUTzx2XK",
      "artist": "Lovelyz",
      "title": "rewind"
   },
   {
      "filename": "\ub7ec\ube14\ub9ac\uc988___Lovelyz_-_Close_To_You_\uad50\ucc28\ud3b8\uc9d1_Stage_Mix.m4a",
      "artist id": "3g34PW5oNmDBxMVUTzx2XK",
      "artist": "Lovelyz",
      "title": "close to you"
   },
   {
      "filename": "[\uad50\ucc28\ud3b8\uc9d1 - Stage Mix] \ub7ec\ube14\ub9ac\uc988 (Lovelyz) - \ubbf8\ubb18\ubbf8\ubb18\ud574 (Mi-myo Mi-myo).m4a",
      "artist id": "3g34PW5oNmDBxMVUTzx2XK",
      "artist": "Lovelyz",
      "title": "mi myo mi myo"
   },
   {
      "filename": "Lovelyz (\ub7ec\ube14\ub9ac\uc988) \u2013 Bookmark (\ucc45\uac08\ud53c) Lyrics (Han-Rom-Eng - Color Coded).m4a",
      "artist id": "3g34PW5oNmDBxMVUTzx2XK",
      "artist": "Lovelyz",
      "title": "bookmark"
   },
   {
      "filename": "Lovelyz \ub7ec\ube14\ub9ac\uc988 \u2013 Doll \uc778\ud615 Lyrics [ Romanization _ Hangul _ Translation ].m4a",
      "artist id": "3g34PW5oNmDBxMVUTzx2XK",
      "artist": "Lovelyz",
      "title": "doll"
   },
   {
      "filename": "\ub7ec\ube14\ub9ac\uc988(Lovelyz)_-Destiny_(\ub098\uc758_\uc9c0\uad6c)-_Official_MV.m4a",
      "artist id": "3g34PW5oNmDBxMVUTzx2XK",
      "artist": "Lovelyz",
      "title": "destiny"
   },
   {
      "filename": "[MV]_Lovelyz(\ub7ec\ube14\ub9ac\uc988)___That_day(\uadf8\ub0a0\uc758_\ub108).m4a",
      "artist id": "3g34PW5oNmDBxMVUTzx2XK",
      "artist": "Lovelyz",
      "title": "that day"
   },
   {
      "filename": "\ub7ec\ube14\ub9ac\uc988(Lovelyz)_\u201c\ucc3e\uc544\uac00\uc138\uc694\u201d_Official_MV.m4a",
      "artist id": "3g34PW5oNmDBxMVUTzx2XK",
      "artist": "Lovelyz",
      "title": "lost n found"
   },
   {
      "filename": "[MV]_\ub7ec\ube14\ub9ac\uc988(Lovelyz)___\uadf8\ub300\uc5d0\uac8c(For_you).m4a",
      "artist id": "3g34PW5oNmDBxMVUTzx2XK",
      "artist": "Lovelyz",
      "title": "for you"
   },
   {
      "filename": "Lovelyz \ub7ec\ube14\ub9ac\uc988 Yoo Jiae \uc720\uc9c0\uc560 - Delight Lyrics MV [ Romanization Hangul Translation ].m4a",
      "artist id": "3g34PW5oNmDBxMVUTzx2XK",
      "artist": "Lovelyz",
      "title": "delight"
   },
   {
      "filename": "[MV] MOMOLAND(\ubaa8\ubaa8\ub79c\ub4dc) _ TIKI TAKA(\ud2f0\ud0a4\ud0c0\uce74).m4a",
      "artist id": "5RR0MLwcjc87wjSw2JYdwx",
      "artist": "Momoland",
      "title": "tiki taka"
   },
   {
      "filename": "[MV]_MOMOLAND(\ubaa8\ubaa8\ub79c\ub4dc)___JJan!_Koong!_Kwang!(\uc9e0\ucff5\ucf85).m4a",
      "artist id": "5RR0MLwcjc87wjSw2JYdwx",
      "artist": "Momoland",
      "title": "jjan! Koong! Kwang!"
   },
   {
      "filename": "[MV]_MOMOLAND(\ubaa8\ubaa8\ub79c\ub4dc)___Freeze(\uaf3c\uc9dd\ub9c8).m4a",
      "artist id": "5RR0MLwcjc87wjSw2JYdwx",
      "artist": "Momoland",
      "title": "freeze"
   },
   {
      "filename": "MOMOLAND_(\ubaa8\ubaa8\ub79c\ub4dc)_-_BBoom_BBoom_(\ubfdc\ubfdc)_-_Areia_Kpop_Remix_#305.m4a",
      "artist id": "5RR0MLwcjc87wjSw2JYdwx",
      "artist": "Momoland",
      "title": "bboom bboom"
   },
   {
      "filename": "[MV]_MOMOLAND(\ubaa8\ubaa8\ub79c\ub4dc)___BAAM.m4a",
      "artist id": "5RR0MLwcjc87wjSw2JYdwx",
      "artist": "Momoland",
      "title": "baam"
   },
   {
      "filename": "[MV]_MOMOLAND(_\ubaa8\ubaa8\ub79c\ub4dc)___Wonderful_love(\uc5b4\ub9c8\uc5b4\ub9c8\ud574).m4a",
      "artist id": "5RR0MLwcjc87wjSw2JYdwx",
      "artist": "Momoland",
      "title": "wonderful love"
   },
   {
      "filename": "NATURE(\ub124\uc774\ucc98)_-\uc378(You'll_Be_Mine)-_M_V.m4a",
      "artist id": "5WUom9mTTEewPdUmI4qnQi",
      "artist": "NATURE",
      "title": "you'll be mine"
   },
   {
      "filename": "NATURE(\ub124\uc774\ucc98)_-\ub0b4\uac00_\uc880_\uc608\ubed0(I'm_So_Pretty)-_M_V.m4a",
      "artist id": "5WUom9mTTEewPdUmI4qnQi",
      "artist": "NATURE",
      "title": "I'm so pretty"
   },
   {
      "filename": "[MV] OH MY GIRL(\uc624\ub9c8\uc774\uac78) _ CUPID.m4a",
      "artist id": "2019zR22qK2RBvCqtudBaI",
      "artist": "Oh My Girl",
      "title": "cupid"
   },
   {
      "filename": "(MV)\uc624\ub9c8\uc774\uac78(OH MY GIRL)_\uc0b4\uc9dd \uc124\ub81c\uc5b4 (Nonstop).m4a",
      "artist id": "2019zR22qK2RBvCqtudBaI",
      "artist": "Oh My Girl",
      "title": "nonstop"
   },
   {
      "filename": "\uc624\ub9c8\uc774\uac78(OH MY GIRL) - \ube44\ubc00\uc815\uc6d0(Secret Garden) \uad50\ucc28\ud3b8\uc9d1(stage mix).m4a",
      "artist id": "2019zR22qK2RBvCqtudBaI",
      "artist": "Oh My Girl",
      "title": "secret garden"
   },
   {
      "filename": "[MV]_\uc624\ub9c8\uc774\uac78(OH_MY_GIRL)___LIAR_LIAR.m4a",
      "artist id": "2019zR22qK2RBvCqtudBaI",
      "artist": "Oh My Girl",
      "title": "liar liar"
   },
   {
      "filename": "[MV]_OH_MY_GIRL(\uc624\ub9c8\uc774\uac78)___Remember_Me(\ubd88\uaf43\ub180\uc774).m4a",
      "artist id": "2019zR22qK2RBvCqtudBaI",
      "artist": "Oh My Girl",
      "title": "remember me"
   },
   {
      "filename": "[MV]_OH_MY_GIRL(\uc624\ub9c8\uc774\uac78)___CLOSER.m4a",
      "artist id": "2019zR22qK2RBvCqtudBaI",
      "artist": "Oh My Girl",
      "title": "closer"
   },
   {
      "filename": "[MV] OH MY GIRL(\uc624\ub9c8\uc774\uac78) _ Coloring Book(\uceec\ub7ec\ub9c1\ubd81).m4a",
      "artist id": "2019zR22qK2RBvCqtudBaI",
      "artist": "Oh My Girl",
      "title": "coloring book"
   },
   {
      "filename": "OH MY GIRL \uc624\ub9c8\uc774\uac78 - NEON - Lyrics (ColorCoded_ENG_HAN_ROM_\uac00\uc0ac).m4a",
      "artist id": "2019zR22qK2RBvCqtudBaI",
      "artist": "Oh My Girl",
      "title": "neon"
   },
   {
      "filename": "[MV] OH MY GIRL(\uc624\ub9c8\uc774\uac78) _ SUPADUPA (\ucc9c\ucc9c\ud788 \ud574\ubd10).m4a",
      "artist id": "2019zR22qK2RBvCqtudBaI",
      "artist": "Oh My Girl",
      "title": "supadupa"
   },
   {
      "filename": "OH MY GIRL (\uc624\ub9c8\uc774\uac78) - 'FLOWER TEA (\uaf43\ucc28)' LYRICS COLOR CODED [HAN_ROM_ENG].m4a",
      "artist id": "2019zR22qK2RBvCqtudBaI",
      "artist": "Oh My Girl",
      "title": "flower tea"
   },
   {
      "filename": "[MV]_OH_MY_GIRL(\uc624\ub9c8\uc774\uac78)___The_fifth_season(\ub2e4\uc12f_\ubc88\uc9f8_\uacc4\uc808)_(SSFWL).m4a",
      "artist id": "2019zR22qK2RBvCqtudBaI",
      "artist": "Oh My Girl",
      "title": "the fifth season"
   },
   {
      "filename": "Shower_(\uc18c\ub098\uae30)_-_Oh_My_Girl_(\uc624\ub9c8\uc774\uac78)_[HAN_ROM_ENG_COLOR_CODED_LYRICS].m4a",
      "artist id": "2019zR22qK2RBvCqtudBaI",
      "artist": "Oh My Girl",
      "title": "shower"
   },
   {
      "filename": "OH MY GIRL - DOLPHIN (Color Coded Lyrics Eng_Rom_Han_\uac00\uc0ac).m4a",
      "artist id": "2019zR22qK2RBvCqtudBaI",
      "artist": "Oh My Girl",
      "title": "dolphin"
   },
   {
      "filename": "OH_MY_GIRL_(\uc624\ub9c8\uc774\uac78)_-_TWILIGHT_[han-rom-eng_color_coded_lyrics_\uac00\uc0ac].m4a",
      "artist id": "2019zR22qK2RBvCqtudBaI",
      "artist": "Oh My Girl",
      "title": "twilight"
   },
   {
      "filename": "[MV]_OH_MY_GIRL(\uc624\ub9c8\uc774\uac78)___Listen_to_my_word(\ub0b4_\uc598\uae38_\ub4e4\uc5b4\ubd10)(A-ing)(Feat._SKULL(\uc2a4\uceec)&H.m4a",
      "artist id": "2019zR22qK2RBvCqtudBaI",
      "artist": "Oh My Girl",
      "title": "listen to my word"
   },
   {
      "filename": "[MV]_OH_MY_GIRL(\uc624\ub9c8\uc774\uac78)___BUNGEE_(Fall_in_Love).m4a",
      "artist id": "2019zR22qK2RBvCqtudBaI",
      "artist": "Oh My Girl",
      "title": "bungee"
   },
   {
      "filename": "[MV]_OH_MY_GIRL_BANHANA(\uc624\ub9c8\uc774\uac78_\ubc18\ud558\ub098)___Banana_allergy_monkey(\ubc14\ub098\ub098_\uc54c\ub7ec\uc9c0_\uc6d0\uc22d\uc774).m4a",
      "artist id": "2019zR22qK2RBvCqtudBaI",
      "artist": "Oh My Girl",
      "title": "banana allergy monkey"
   },
   {
      "filename": "Red Velvet (\ub808\ub4dc\ubca8\ubcb3) \u2014 Lady's Room (Han-Rom-Eng Color Coded Lyrics by Red Heart).m4a",
      "artist id": "1z4g3DjTBBZKhvAroFlhOM",
      "artist": "Red Velvet",
      "title": "lady's room"
   },
   {
      "filename": "Red_Velvet_(\ub808\ub4dc\ubca8\ubcb3)_\u2013_First_Time_(\ucc98\uc74c\uc778\uac00\uc694)_Lyrics_(Han__Rom__Eng__Color_Coded).m4a",
      "artist id": "1z4g3DjTBBZKhvAroFlhOM",
      "artist": "Red Velvet",
      "title": "first time"
   },
   {
      "filename": "Red_Velvet_(\ub808\ub4dc\ubca8\ubcb3)_-_Mojito_(\uc5ec\ub984\ube5b)_[HANROMENG_Color_Coded_Lyrics].m4a",
      "artist id": "1z4g3DjTBBZKhvAroFlhOM",
      "artist": "Red Velvet",
      "title": "mojito"
   },
   {
      "filename": "Red_Velvet_(\ub808\ub4dc\ubca8\ubcb3)_-_Hear_The_Sea_(\ubc14\ub2e4\uac00_\ub4e4\ub824)_[HANROMENG_Color_Coded_Lyrics].m4a",
      "artist id": "1z4g3DjTBBZKhvAroFlhOM",
      "artist": "Red Velvet",
      "title": "hear the sea"
   },
   {
      "filename": "RED_VELVET_(\ub808\ub4dc\ubca8\ubcb3)_-_Eyes_Locked,_Hands_Locked_(\ub208_\ub9de\ucd94\uace0,_\uc190_\ub9de\ub300\uace0)_(Color_Coded_Ly.m4a",
      "artist id": "1z4g3DjTBBZKhvAroFlhOM",
      "artist": "Red Velvet",
      "title": "eys locked, hands locked"
   },
   {
      "filename": "[Color_Coded_Han_Eng_Rom]_Red_Velvet_-_Candy.m4a",
      "artist id": "1z4g3DjTBBZKhvAroFlhOM",
      "artist": "Red Velvet",
      "title": "candy"
   },
   {
      "filename": "RED_VELVET_(\ub808\ub4dc\ubca8\ubcb3)_-_'CARPOOL'_(\uce74\ud480)_Lyrics_[Color_Coded_Han_Rom_Eng].m4a",
      "artist id": "1z4g3DjTBBZKhvAroFlhOM",
      "artist": "Red Velvet",
      "title": "carpool"
   },
   {
      "filename": "Red_Velvet_(\ub808\ub4dc\ubca8\ubcb3)_\u2013_Rose_Scent_Breeze_(\uc7a5\ubbf8\uaf43_\ud5a5\uae30\ub294_\ubc14\ub78c\uc5d0_\ub0a0\ub9ac\uace0)_Lyrics_(HAN_-_ROM_-_.m4a",
      "artist id": "1z4g3DjTBBZKhvAroFlhOM",
      "artist": "Red Velvet",
      "title": "rose scent breeze"
   },
   {
      "filename": "Red_Velvet_\ub808\ub4dc\ubca8\ubcb3_'\ube68\uac04_\ub9db_(Red_Flavor)'_MV.m4a",
      "artist id": "1z4g3DjTBBZKhvAroFlhOM",
      "artist": "Red Velvet",
      "title": "red flavor"
   },
   {
      "filename": "Red_Velvet_-_Moonlight_Melody_lyrics_(Color_Coded_Han-Rom-Eng).m4a",
      "artist id": "1z4g3DjTBBZKhvAroFlhOM",
      "artist": "Red Velvet",
      "title": "moonlight melody"
   },
   {
      "filename": "Red_Velvet_\ub808\ub4dc\ubca8\ubcb3_'Bad_Boy'_MV.m4a",
      "artist id": "1z4g3DjTBBZKhvAroFlhOM",
      "artist": "Red Velvet",
      "title": "bad boy"
   },
   {
      "filename": "Red_Velvet_\ub808\ub4dc\ubca8\ubcb3_'RBB_(Really_Bad_Boy)'_MV.m4a",
      "artist id": "1z4g3DjTBBZKhvAroFlhOM",
      "artist": "Red Velvet",
      "title": "really bad boy"
   },
   {
      "filename": "Red_Velvet_\ub808\ub4dc\ubca8\ubcb3_'Rookie'_MV.m4a",
      "artist id": "1z4g3DjTBBZKhvAroFlhOM",
      "artist": "Red Velvet",
      "title": "rookie"
   },
   {
      "filename": "[STATION]_Red_Velvet_\ub808\ub4dc\ubca8\ubcb3_'Would_U'_MV.m4a",
      "artist id": "1z4g3DjTBBZKhvAroFlhOM",
      "artist": "Red Velvet",
      "title": "would u"
   },
   {
      "filename": "Red_Velvet_-_See_The_Stars_(Hotel_Del_Luna_OST_8)_Lyrics_Color_Coded_(Han_Ro.m4a",
      "artist id": "1z4g3DjTBBZKhvAroFlhOM",
      "artist": "Red Velvet",
      "title": "see the stars"
   },
   {
      "filename": "Red_Velvet_\ub808\ub4dc\ubca8\ubcb3_'Psycho'_MV.m4a",
      "artist id": "1z4g3DjTBBZKhvAroFlhOM",
      "artist": "Red Velvet",
      "title": "psycho"
   },
   {
      "filename": "Red_Velvet_-_Wish_Tree_(\uc138\uac00\uc9c0_\uc18c\uc6d0)_(Color_Coded_HanRomEng_Lyrics).m4a",
      "artist id": "1z4g3DjTBBZKhvAroFlhOM",
      "artist": "Red Velvet",
      "title": "wish tree"
   },
   {
      "filename": "Red_Velvet_(\ub808\ub4dc\ubca8\ubcb3)_-_Jumpin'_Lyrics_Color_Coded_(Han_Rom_Eng).m4a",
      "artist id": "1z4g3DjTBBZKhvAroFlhOM",
      "artist": "Red Velvet",
      "title": "jumpin'"
   },
   {
      "filename": "LP_-_Red_Velvet_(\ub808\ub4dc\ubca8\ubcb3)_[HAN_ROM_ENG_COLOR_CODED_LYRICS].m4a",
      "artist id": "1z4g3DjTBBZKhvAroFlhOM",
      "artist": "Red Velvet",
      "title": "lp"
   },
   {
      "filename": "Red_Velvet_(\ub808\ub4dc\ubca8\ubcb3)_\u2013_Sunny_Side_Up!_Lyrics_(Color_Coded_Han_Rom_Eng).m4a",
      "artist id": "1z4g3DjTBBZKhvAroFlhOM",
      "artist": "Red Velvet",
      "title": "sunny side up!"
   },
   {
      "filename": "Red_Velvet_\ub808\ub4dc\ubca8\ubcb3_'Ice_Cream_Cake'_MV.m4a",
      "artist id": "1z4g3DjTBBZKhvAroFlhOM",
      "artist": "Red Velvet",
      "title": "ice cream cake"
   },
   {
      "filename": "Red_Velvet_-_Happily_Ever_After_Lyrics_(Han-Rom-Eng)_Color_Coded.m4a",
      "artist id": "1z4g3DjTBBZKhvAroFlhOM",
      "artist": "Red Velvet",
      "title": "happily ever after"
   },
   {
      "filename": "Red_Velvet_-_Lucky_Girl_(Color_Coded_Han-Rom-Eng_Lyrics)_-_by_Yankat.m4a",
      "artist id": "1z4g3DjTBBZKhvAroFlhOM",
      "artist": "Red Velvet",
      "title": "lucky girl"
   },
   {
      "filename": "Red_Velvet_\ub808\ub4dc\ubca8\ubcb3_'\uc9d0\uc0b4\ub77c\ube54_(Zimzalabim)'_MV.m4a",
      "artist id": "1z4g3DjTBBZKhvAroFlhOM",
      "artist": "Red Velvet",
      "title": "zimzalabim"
   },
   {
      "filename": "red_velvet_(\ub808\ub4dc\ubca8\ubcb3)_-_bing_bing_lyrics_[han-rom-eng_color_coded].m4a",
      "artist id": "1z4g3DjTBBZKhvAroFlhOM",
      "artist": "Red Velvet",
      "title": "bing bing"
   },
   {
      "filename": "[STATION]_Red_Velvet_\ub808\ub4dc\ubca8\ubcb3_'\ud658\uc0dd_(Rebirth)'_MV.m4a",
      "artist id": "1z4g3DjTBBZKhvAroFlhOM",
      "artist": "Red Velvet",
      "title": "rebirth"
   },
   {
      "filename": "Red_Velvet_-_Parade_(Color-coded_Lyrics)_HanRomEng.m4a",
      "artist id": "1z4g3DjTBBZKhvAroFlhOM",
      "artist": "Red Velvet",
      "title": "parade"
   },
   {
      "filename": "Red_Velvet_-_Take_It_Slow_[EngRomHan]_Picture___Color_Coded_HD.m4a",
      "artist id": "1z4g3DjTBBZKhvAroFlhOM",
      "artist": "Red Velvet",
      "title": "take it slow"
   },
   {
      "filename": "Red_Velvet_\u2013_With_You_lyrics_(Color_Coded_Han-Rom-Eng).m4a",
      "artist id": "1z4g3DjTBBZKhvAroFlhOM",
      "artist": "Red Velvet",
      "title": "with you"
   },
   {
      "filename": "Red_Velvet_(\ub808\ub4dc\ubca8\ubcb3)_-_Remember_Forever_Lyrics_[Color_Coded_HAN_ROM_ENG].m4a",
      "artist id": "1z4g3DjTBBZKhvAroFlhOM",
      "artist": "Red Velvet",
      "title": "remember forever"
   },
   {
      "filename": "Red_Velvet_\ub808\ub4dc\ubca8\ubcb3_'Dumb_Dumb'_MV.m4a",
      "artist id": "1z4g3DjTBBZKhvAroFlhOM",
      "artist": "Red Velvet",
      "title": "dumb dumb"
   },
   {
      "filename": "[STATION] Red Velvet \ub808\ub4dc\ubca8\ubcb3 'Milky Way' Live Video - Our Beloved BoA #4.m4a",
      "artist id": "1z4g3DjTBBZKhvAroFlhOM",
      "artist": "Red Velvet",
      "title": "milky way"
   },
   {
      "filename": "Red_Velvet_In_&_Out_Lyrics_(\ub808\ub4dc\ubca8\ubcb3_In_&_Out_\uac00\uc0ac)_[Color_Coded_Lyrics_Han_Rom_En.m4a",
      "artist id": "1z4g3DjTBBZKhvAroFlhOM",
      "artist": "Red Velvet",
      "title": "in & out"
   },
   {
      "filename": "Red_Velvet_\ub808\ub4dc\ubca8\ubcb3_'\uc74c\ud30c\uc74c\ud30c_(Umpah_Umpah)'_MV.m4a",
      "artist id": "1z4g3DjTBBZKhvAroFlhOM",
      "artist": "Red Velvet",
      "title": "umpah umpah"
   },
   {
      "filename": "Red_Velvet_\ub808\ub4dc\ubca8\ubcb3_'\ud53c\uce74\ubd80_(Peek-A-Boo)'_MV.m4a",
      "artist id": "1z4g3DjTBBZKhvAroFlhOM",
      "artist": "Red Velvet",
      "title": "peek a boo"
   },
   {
      "filename": "Red_Velvet_-_Milkshake_(Color-coded_Lyrics)_Han_Rom_Eng.m4a",
      "artist id": "1z4g3DjTBBZKhvAroFlhOM",
      "artist": "Red Velvet",
      "title": "milkshake"
   },
   {
      "filename": "Red_Velvet_(\ub808\ub4dc\ubca8\ubcb3)_-_Love_is_The_Way_Lyrics_Color_Coded_(Han_Rom_Eng).m4a",
      "artist id": "1z4g3DjTBBZKhvAroFlhOM",
      "artist": "Red Velvet",
      "title": "love is the way"
   },
   {
      "filename": "Red_Velvet_-_Little_Little_Lyrics_(Han_Rom_Eng)_Color_Coded.m4a",
      "artist id": "1z4g3DjTBBZKhvAroFlhOM",
      "artist": "Red Velvet",
      "title": "little little"
   },
   {
      "filename": "Red Velvet (\ub808\ub4dc\ubca8\ubcb3) - FUTURE (\ubbf8\ub798) - START-UP OST Part.1 (Color Coded Lyrics Han_Rom_Eng_\uac00\uc0ac).m4a",
      "artist id": "1z4g3DjTBBZKhvAroFlhOM",
      "artist": "Red Velvet",
      "title": "future"
   },
   {
      "filename": "Red_Velvet_\ub808\ub4dc\ubca8\ubcb3_'\ub7ec\uc2dc\uc548_\ub8f0\ub81b_(Russian_Roulette)'_MV.m4a",
      "artist id": "1z4g3DjTBBZKhvAroFlhOM",
      "artist": "Red Velvet",
      "title": "russian roulette"
   },
   {
      "filename": "Red_Velvet_\u30ec\u30c3\u30c9\u30d9\u30eb\u30d9\u30c3\u30c9_'#Cookie_Jar'_MV.m4a",
      "artist id": "1z4g3DjTBBZKhvAroFlhOM",
      "artist": "Red Velvet",
      "title": "#cookie jar"
   },
   {
      "filename": "Red_Velvet_-_Ladies_Night_(\ub808\ub4dc\ubca8\ubcb3_-_Ladies_Night)_[Color_Coded_Lyrics_Han_Rom_.m4a",
      "artist id": "1z4g3DjTBBZKhvAroFlhOM",
      "artist": "Red Velvet",
      "title": "ladies night"
   },
   {
      "filename": "Red_Velvet_\u30ec\u30c3\u30c9\u30d9\u30eb\u30d9\u30c3\u30c9_\u2018SAPPY\u2019_MV.m4a",
      "artist id": "1z4g3DjTBBZKhvAroFlhOM",
      "artist": "Red Velvet",
      "title": "sappy"
   },
   {
      "filename": "RED_VELVET_(\ub808\ub4dc\ubca8\ubcb3)_-_MR._E_[Color_CodedRomHanEng].m4a",
      "artist id": "1z4g3DjTBBZKhvAroFlhOM",
      "artist": "Red Velvet",
      "title": "mr. e"
   },
   {
      "filename": "Red_Velvet_\ub808\ub4dc\ubca8\ubcb3_'\ud589\ubcf5_(Happiness)'_MV.m4a",
      "artist id": "1z4g3DjTBBZKhvAroFlhOM",
      "artist": "Red Velvet",
      "title": "happiness"
   },
   {
      "filename": "Red_Velvet_-_Sassy_me_lyrics_(Color_Coded_Han-Rom-Eng).m4a",
      "artist id": "1z4g3DjTBBZKhvAroFlhOM",
      "artist": "Red Velvet",
      "title": "sassy me"
   },
   {
      "filename": "Red_Velvet_(\ub808\ub4dc\ubca8\ubcb3)_-_You_Better_Know_[HAN-ROM-ENG_Color_Coded_Lyrics].m4a",
      "artist id": "1z4g3DjTBBZKhvAroFlhOM",
      "artist": "Red Velvet",
      "title": "you better know"
   },
   {
      "filename": "Red_Velvet_\ub808\ub4dc\ubca8\ubcb3_'Power_Up'_MV.m4a",
      "artist id": "1z4g3DjTBBZKhvAroFlhOM",
      "artist": "Red Velvet",
      "title": "power up"
   },
   {
      "filename": "RED VELVET (\ub808\ub4dc\ubc8c\ubcb3) - TIME TO LOVE [COLOR CODED LYRICS _ HAN+ROM+ENG].m4a",
      "artist id": "1z4g3DjTBBZKhvAroFlhOM",
      "artist": "Red Velvet",
      "title": "time to love"
   },
   {
      "filename": "Red Velvet \ub808\ub4dc\ubca8\ubcb3 Somethin Kinda Crazy Lyrics Eng Sub + Romanization.m4a",
      "artist id": "1z4g3DjTBBZKhvAroFlhOM",
      "artist": "Red Velvet",
      "title": "somethin kinda crazy"
   },
   {
      "filename": "Red Velvet - Huff N Puff [Eng_Rom_Han] Picture + Color Coded HD.m4a",
      "artist id": "1z4g3DjTBBZKhvAroFlhOM",
      "artist": "Red Velvet",
      "title": "huff n puff"
   },
   {
      "filename": "red_velvet_(\ub808\ub4dc\ubca8\ubcb3)_-_blue_lemonade_(color_coded_lyrics_eng_rom_han).m4a",
      "artist id": "1z4g3DjTBBZKhvAroFlhOM",
      "artist": "Red Velvet",
      "title": "blue lemonade"
   },
   {
      "filename": "Rocket Punch(\ub85c\ucf13\ud380\uce58) 'THE THE' Special Choreography Video.m4a",
      "artist id": "4hozqATxbpy9TwKWRT8QVO",
      "artist": "Rocket Punch",
      "title": "the the"
   },
   {
      "filename": "\ub85c\ucf13\ud380\uce58(Rocket Punch) 'JUICY' MV.m4a",
      "artist id": "4hozqATxbpy9TwKWRT8QVO",
      "artist": "Rocket Punch",
      "title": "juicy"
   },
   {
      "filename": "Rocket Punch(\ub85c\ucf13\ud380\uce58) \u2018\ube54\ubc24\ubd90(BIM BAM BUM)\u2019 Official MV.m4a",
      "artist id": "4hozqATxbpy9TwKWRT8QVO",
      "artist": "Rocket Punch",
      "title": "bim bam bum"
   },
   {
      "filename": "Rocket Punch (\ub85c\ucf13\ud380\uce58) - TWINKLE STAR - Lyrics (Color Coded_ENG_HAN_ROM_\uac00\uc0ac).m4a",
      "artist id": "4hozqATxbpy9TwKWRT8QVO",
      "artist": "Rocket Punch",
      "title": "twinkle star"
   },
   {
      "filename": "Rocket Punch(\ub85c\ucf13\ud380\uce58) 'BOUNCY' MV.m4a",
      "artist id": "4hozqATxbpy9TwKWRT8QVO",
      "artist": "Rocket Punch",
      "title": "bouncy"
   },
   {
      "filename": "ROCKET PUNCH (\ub7ec\ucf13\ud380\uce58) - 'Summer Night' (\uc5ec\ub984\ubc24) [Color Coded Lyrics_Han - Rom - Eng].m4a",
      "artist id": "4hozqATxbpy9TwKWRT8QVO",
      "artist": "Rocket Punch",
      "title": "summer night"
   },
   {
      "filename": "ROCKET PUNCH(\ub85c\ucf13\ud380\uce58) - LUCID DREAM [COLOR CODED HAN_ROM_ENG LYRICS].m4a",
      "artist id": "4hozqATxbpy9TwKWRT8QVO",
      "artist": "Rocket Punch",
      "title": "lucid dream"
   },
   {
      "filename": "Rocket Punch (\ub85c\ucf13\ud380\uce58) - SUMMER PUNCH! - Lyrics (Color Coded_ENG_HAN_ROM_\uac00\uc0ac).m4a",
      "artist id": "4hozqATxbpy9TwKWRT8QVO",
      "artist": "Rocket Punch",
      "title": "summer punch!"
   },
   {
      "filename": "\uc2dc\ud06c\ub9bf (SECRET) - YooHoo MV.m4a",
      "artist id": "503DjcVO5Ku1NgLPhVuNg7",
      "artist": "Secret",
      "title": "yoohoo"
   },
   {
      "filename": "\uc2dc\ud06c\ub9bf (Secret) _ \ubcc4\ube5b\ub2ec\ube5b (Starlight Moonlight) MV.m4a",
      "artist id": "503DjcVO5Ku1NgLPhVuNg7",
      "artist": "Secret",
      "title": "starlight moonlight"
   },
   {
      "filename": "\uc2dc\ud06c\ub9bf (SECRET) - I Do I Do MV.m4a",
      "artist id": "503DjcVO5Ku1NgLPhVuNg7",
      "artist": "Secret",
      "title": "I do I do"
   },
   {
      "filename": "TRI.BE - DOOM DOOM TA.m4a",
      "artist id": "6BgYuNomEs12UIrnxhWE9a",
      "artist": "TRI.BE",
      "title": "doom doom ta"
   },
   {
      "filename": "TWICE_-_Signal_[MV].m4a",
      "artist id": "7n2Ycct7Beij7Dj7meI4X0",
      "artist": "TWICE",
      "title": "signal"
   },
   {
      "filename": "TWICE_-_Like_OOH-AHH(OOH-AHH\ud558\uac8c)_[MV].m4a",
      "artist id": "7n2Ycct7Beij7Dj7meI4X0",
      "artist": "TWICE",
      "title": "like ooh-ahh"
   },
   {
      "filename": "TWICE_(\ud2b8\uc640\uc774\uc2a4)_Jelly_Jelly_Lyrics_(Han-Rom-Eng)_Color_Coded.m4a",
      "artist id": "7n2Ycct7Beij7Dj7meI4X0",
      "artist": "TWICE",
      "title": "jelly jelly"
   },
   {
      "filename": "TWICE_-_Dance_The_Night_Away_[MV].m4a",
      "artist id": "7n2Ycct7Beij7Dj7meI4X0",
      "artist": "TWICE",
      "title": "dance the night away"
   },
   {
      "filename": "TWICE_-_Feel_Special_[MV].m4a",
      "artist id": "7n2Ycct7Beij7Dj7meI4X0",
      "artist": "TWICE",
      "title": "feel special"
   },
   {
      "filename": "TWICE_(\ud2b8\uc640\uc774\uc2a4)_-STRAWBERRY-_(Color_Coded_Lyrics_Eng_Rom_Han_\uac00\uc0ac).m4a",
      "artist id": "7n2Ycct7Beij7Dj7meI4X0",
      "artist": "TWICE",
      "title": "strawberry"
   },
   {
      "filename": "TWICE\u300cHAPPY_HAPPY\u300dMusic_Video.m4a",
      "artist id": "7n2Ycct7Beij7Dj7meI4X0",
      "artist": "TWICE",
      "title": "happy happy"
   },
   {
      "filename": "TWICE\u300cOne_More_Time\u300dMusic_Video.m4a",
      "artist id": "7n2Ycct7Beij7Dj7meI4X0",
      "artist": "TWICE",
      "title": "one more time"
   },
   {
      "filename": "Twice_(\ud2b8\uc640\uc774\uc2a4)_Truth_Lyrics_(Color_Coded_Han-Rom-Eng)_-_by_Soshi_Lyrics.m4a",
      "artist id": "7n2Ycct7Beij7Dj7meI4X0",
      "artist": "TWICE",
      "title": "truth"
   },
   {
      "filename": "TWICE_-_TT_[MV].m4a",
      "artist id": "7n2Ycct7Beij7Dj7meI4X0",
      "artist": "TWICE",
      "title": "tt"
   },
   {
      "filename": "TWICE_(\ud2b8\uc640\uc774\uc2a4)_Woohoo_Lyrics_(Color_Coded_Han-Rom-Eng)_-_by_Soshi_Lyrics.m4a",
      "artist id": "7n2Ycct7Beij7Dj7meI4X0",
      "artist": "TWICE",
      "title": "woohoo"
   },
   {
      "filename": "TWICE_-_Likey_[MV].m4a",
      "artist id": "7n2Ycct7Beij7Dj7meI4X0",
      "artist": "TWICE",
      "title": "likey"
   },
   {
      "filename": "TWICE_\u300cFake_&_True\u300d_Music_Video.m4a",
      "artist id": "7n2Ycct7Beij7Dj7meI4X0",
      "artist": "TWICE",
      "title": "fake & true"
   },
   {
      "filename": "TWICE_-_Cheer_Up_[MV].m4a",
      "artist id": "7n2Ycct7Beij7Dj7meI4X0",
      "artist": "TWICE",
      "title": "cheer up"
   },
   {
      "filename": "TWICE -I CAN'T STOP ME- MV.m4a",
      "artist id": "7n2Ycct7Beij7Dj7meI4X0",
      "artist": "TWICE",
      "title": "I can't stop me"
   },
   {
      "filename": "TWICE_(\ud2b8\uc640\uc774\uc2a4)_Precious_Love_Lyrics_(Color_Coded_Han-Rom-Eng)_-_by_Soshi_Lyric.m4a",
      "artist id": "7n2Ycct7Beij7Dj7meI4X0",
      "artist": "TWICE",
      "title": "precious love"
   },
   {
      "filename": "TWICE\u300cI_WANT_YOU_BACK\u300dMusic_Video.m4a",
      "artist id": "7n2Ycct7Beij7Dj7meI4X0",
      "artist": "TWICE",
      "title": "I want you back"
   },
   {
      "filename": "TWICE_-_FANCY_[MV].m4a",
      "artist id": "7n2Ycct7Beij7Dj7meI4X0",
      "artist": "TWICE",
      "title": "fancy"
   },
   {
      "filename": "TWICE_-_Heart_Shaker_[MV].m4a",
      "artist id": "7n2Ycct7Beij7Dj7meI4X0",
      "artist": "TWICE",
      "title": "heart shaker"
   },
   {
      "filename": "TWICE_-_YES_or_YES_[MV].m4a",
      "artist id": "7n2Ycct7Beij7Dj7meI4X0",
      "artist": "TWICE",
      "title": "yes or yes"
   },
   {
      "filename": "TWICE\u300cWake_Me_Up\u300dMusic_Video.m4a",
      "artist id": "7n2Ycct7Beij7Dj7meI4X0",
      "artist": "TWICE",
      "title": "wake me up"
   },
   {
      "filename": "TWICE\u300cBDZ\u300dMusic_Video.m4a",
      "artist id": "7n2Ycct7Beij7Dj7meI4X0",
      "artist": "TWICE",
      "title": "bdz"
   },
   {
      "filename": "TWICE_(\ud2b8\uc640\uc774\uc2a4)_-_HO!_Lyrics_[Color_Coded_HAN_ROM_ENG].m4a",
      "artist id": "7n2Ycct7Beij7Dj7meI4X0",
      "artist": "TWICE",
      "title": "ho!"
   },
   {
      "filename": "TWICE\u300cBreakthrough\u300dMusic_Video.m4a",
      "artist id": "7n2Ycct7Beij7Dj7meI4X0",
      "artist": "TWICE",
      "title": "breakthrough"
   },
   {
      "filename": "TWICE\u300cCandy_Pop\u300dMusic_Video.m4a",
      "artist id": "7n2Ycct7Beij7Dj7meI4X0",
      "artist": "TWICE",
      "title": "candy pop"
   },
   {
      "filename": "TWICE\u300cBRAND_NEW_GIRL\u300dMusic_Video.m4a",
      "artist id": "7n2Ycct7Beij7Dj7meI4X0",
      "artist": "TWICE",
      "title": "brand new girl"
   },
   {
      "filename": "TWICE_-_What_is_Love_[MV].m4a",
      "artist id": "7n2Ycct7Beij7Dj7meI4X0",
      "artist": "TWICE",
      "title": "what is love"
   },
   {
      "filename": "TWICE_-_Knock_Knock_[MV].m4a",
      "artist id": "7n2Ycct7Beij7Dj7meI4X0",
      "artist": "TWICE",
      "title": "knock knock"
   },
   {
      "filename": "TWICE_(\ud2b8\uc640\uc774\uc2a4)_Next_Page_Lyrics_(Han-Rom-Eng)_Color_Coded.m4a",
      "artist id": "7n2Ycct7Beij7Dj7meI4X0",
      "artist": "TWICE",
      "title": "next page"
   },
   {
      "filename": "TWICE \u300cFanfare\u300dMusic Video.m4a",
      "artist id": "7n2Ycct7Beij7Dj7meI4X0",
      "artist": "TWICE",
      "title": "fanfare"
   },
   {
      "filename": "[MV] Weeekly(\u110b\u1171\u110f\u1173\u11af\u1105\u1175) _ After School.m4a",
      "artist id": "73B9bjqS2Z5KLXNGqXf64m",
      "artist": "Weeekly",
      "title": "after school"
   },
   {
      "filename": "Weki Meki \u110b\u1171\u110f\u1175\u1106\u1175\u110f\u1175 - DAZZLE DAZZLE MV.m4a",
      "artist id": "5LWkv2hDbDwZL3zNwZYNPx",
      "artist": "Weki Meki",
      "title": "dazzle dazzle"
   },
   {
      "filename": "Weki Meki \u110b\u1171\u110f\u1175\u1106\u1175\u110f\u1175 - Crush MV.m4a",
      "artist id": "5LWkv2hDbDwZL3zNwZYNPx",
      "artist": "Weki Meki",
      "title": "crush"
   },
   {
      "filename": "[MV] Weki Meki(\uc704\ud0a4\ubbf8\ud0a4) _ OOPSY.m4a",
      "artist id": "5LWkv2hDbDwZL3zNwZYNPx",
      "artist": "Weki Meki",
      "title": "oopsy"
   },
   {
      "filename": "Weki Meki \u110b\u1171\u110f\u1175\u1106\u1175\u110f\u1175 - Picky Picky MV.m4a",
      "artist id": "5LWkv2hDbDwZL3zNwZYNPx",
      "artist": "Weki Meki",
      "title": "picky picky"
   },
   {
      "filename": "Weki Meki \u110b\u1171\u110f\u1175\u1106\u1175\u110f\u1175 - Tiki-Taka(99%) MV.m4a",
      "artist id": "5LWkv2hDbDwZL3zNwZYNPx",
      "artist": "Weki Meki",
      "title": "tiki-taka(99%)"
   },
   {
      "filename": "Weki Meki \uc704\ud0a4\ubbf8\ud0a4 - COOL MV.m4a",
      "artist id": "5LWkv2hDbDwZL3zNwZYNPx",
      "artist": "Weki Meki",
      "title": "cool"
   },
   {
      "filename": "[MV] WJSN(\uc6b0\uc8fc\uc18c\ub140) _ BUTTERFLY.m4a",
      "artist id": "6hhqsQZhtp9hfaZhSd0VSD",
      "artist": "WJSN",
      "title": "butterfly"
   },
   {
      "filename": "[MV] YUKIKA(\uc720\ud0a4\uce74) _ Cherries Jubiles(\uc88b\uc544\ud558\uace0 \uc788\uc5b4\uc694).m4a",
      "artist id": "4RfI1z9u2xIc5Qnqac4JbO",
      "artist": "Yukika",
      "title": "cherries jubiles"
   },
   {
      "filename": "[MV] YUKIKA(\uc720\ud0a4\uce74) _ NEON(\ub124\uc628).m4a",
      "artist id": "4RfI1z9u2xIc5Qnqac4JbO",
      "artist": "Yukika",
      "title": "neon"
   },
   {
      "filename": "\uc720\ud0a4\uce74 YUKIKA - \u300cYesterday\u300d \uc548\ubb34 \uc601\uc0c1 Choreography Video.m4a",
      "artist id": "4RfI1z9u2xIc5Qnqac4JbO",
      "artist": "Yukika",
      "title": "yesterday"
   },
   {
      "filename": "[MV] \uc720\ud0a4\uce74 YUKIKA - \u300c\uc11c\uc6b8\uc5ec\uc790 (SOUL LADY)\u300d Official Music Video.m4a",
      "artist id": "4RfI1z9u2xIc5Qnqac4JbO",
      "artist": "Yukika",
      "title": "soul candy"
   }
]